{
  "PID": -1,
  "gesture": "baseline",
  "task": "digitSelector",
  "target": 4,
  "block": 0,
  "startTime": 56544,
  "endTime": 60132,
  "frames": [
    {
      "activity": "drawCalled",
      "state": "NoHands",
      "cursor_X": 811.1954,
      "cursor_y": 721.9228,
      "slider_position_X": 600.0,
      "slider_value": 0
    },
    {
      "activity": "StateTransition",
      "state": "NoHands",
      "message": "Transitioning from states NoHands to NoPinchDetected",
      "cursor_X": 811.1954,
      "cursor_y": 721.9228,
      "slider_position_X": 600.0,
      "slider_value": 0
    },
    {
      "activity": "drawCalled",
      "state": "NoPinchDetected",
      "cursor_X": 810.6577,
      "cursor_y": 721.8901,
      "slider_position_X": 600.0,
      "slider_value": 0
    },
    {
      "activity": "gestureDetected",
      "state": "NoPinchDetected",
      "message": "Gesture detected",
      "cursor_X": 810.6577,
      "cursor_y": 721.8901,
      "slider_position_X": 600.0,
      "slider_value": 0
    },
    {
      "activity": "StateTransition",
      "state": "NoPinchDetected",
      "message": "Transitioning from states NoPinchDetected to PinchDetected",
      "cursor_X": 810.6577,
      "cursor_y": 721.8901,
      "slider_position_X": 600.0,
      "slider_value": 0
    },
    {
      "activity": "drawCalled",
      "state": "PinchDetected",
      "cursor_X": 810.1142,
      "cursor_y": 721.86035,
      "slider_position_X": 600.0,
      "slider_value": 0
    },
    {
      "activity": "gestureDetected",
      "state": "PinchDetected",
      "message": "Gesture detected not on slider",
      "cursor_X": 810.1142,
      "cursor_y": 721.86035,
      "slider_position_X": 600.0,
      "slider_value": 0
    },
    {
      "activity": "drawCalled",
      "state": "PinchDetected",
      "cursor_X": 809.6101,
      "cursor_y": 721.837,
      "slider_position_X": 600.0,
      "slider_value": 0
    },
    {
      "activity": "gestureDetected",
      "state": "PinchDetected",
      "message": "Gesture detected not on slider",
      "cursor_X": 809.6101,
      "cursor_y": 721.837,
      "slider_position_X": 600.0,
      "slider_value": 0
    },
    {
      "activity": "drawCalled",
      "state": "PinchDetected",
      "cursor_X": 809.18494,
      "cursor_y": 721.8154,
      "slider_position_X": 600.0,
      "slider_value": 0
    },
    {
      "activity": "gestureDetected",
      "state": "PinchDetected",
      "message": "Gesture detected not on slider",
      "cursor_X": 809.18494,
      "cursor_y": 721.8154,
      "slider_position_X": 600.0,
      "slider_value": 0
    },
    {
      "activity": "drawCalled",
      "state": "PinchDetected",
      "cursor_X": 808.8447,
      "cursor_y": 721.80414,
      "slider_position_X": 600.0,
      "slider_value": 0
    },
    {
      "activity": "gestureDetected",
      "state": "PinchDetected",
      "message": "Gesture detected not on slider",
      "cursor_X": 808.8447,
      "cursor_y": 721.80414,
      "slider_position_X": 600.0,
      "slider_value": 0
    },
    {
      "activity": "drawCalled",
      "state": "PinchDetected",
      "cursor_X": 808.73535,
      "cursor_y": 721.7978,
      "slider_position_X": 600.0,
      "slider_value": 0
    },
    {
      "activity": "gestureDetected",
      "state": "PinchDetected",
      "message": "Gesture detected not on slider",
      "cursor_X": 808.73535,
      "cursor_y": 721.7978,
      "slider_position_X": 600.0,
      "slider_value": 0
    },
    {
      "activity": "drawCalled",
      "state": "PinchDetected",
      "cursor_X": 808.6732,
      "cursor_y": 721.79425,
      "slider_position_X": 600.0,
      "slider_value": 0
    },
    {
      "activity": "gestureDetected",
      "state": "PinchDetected",
      "message": "Gesture detected not on slider",
      "cursor_X": 808.6732,
      "cursor_y": 721.79425,
      "slider_position_X": 600.0,
      "slider_value": 0
    },
    {
      "activity": "drawCalled",
      "state": "PinchDetected",
      "cursor_X": 808.63947,
      "cursor_y": 721.7917,
      "slider_position_X": 600.0,
      "slider_value": 0
    },
    {
      "activity": "gestureDetected",
      "state": "PinchDetected",
      "message": "Gesture detected not on slider",
      "cursor_X": 808.63947,
      "cursor_y": 721.7917,
      "slider_position_X": 600.0,
      "slider_value": 0
    },
    {
      "activity": "drawCalled",
      "state": "PinchDetected",
      "cursor_X": 808.6167,
      "cursor_y": 721.7892,
      "slider_position_X": 600.0,
      "slider_value": 0
    },
    {
      "activity": "gestureDetected",
      "state": "PinchDetected",
      "message": "Gesture detected not on slider",
      "cursor_X": 808.6167,
      "cursor_y": 721.7892,
      "slider_position_X": 600.0,
      "slider_value": 0
    },
    {
      "activity": "drawCalled",
      "state": "PinchDetected",
      "cursor_X": 808.61,
      "cursor_y": 721.78827,
      "slider_position_X": 600.0,
      "slider_value": 0
    },
    {
      "activity": "gestureDetected",
      "state": "PinchDetected",
      "message": "Gesture detected not on slider",
      "cursor_X": 808.61,
      "cursor_y": 721.78827,
      "slider_position_X": 600.0,
      "slider_value": 0
    },
    {
      "activity": "drawCalled",
      "state": "PinchDetected",
      "cursor_X": 808.6032,
      "cursor_y": 721.78735,
      "slider_position_X": 600.0,
      "slider_value": 0
    },
    {
      "activity": "gestureDetected",
      "state": "PinchDetected",
      "message": "Gesture detected not on slider",
      "cursor_X": 808.6032,
      "cursor_y": 721.78735,
      "slider_position_X": 600.0,
      "slider_value": 0
    },
    {
      "activity": "drawCalled",
      "state": "PinchDetected",
      "cursor_X": 808.5991,
      "cursor_y": 721.7869,
      "slider_position_X": 600.0,
      "slider_value": 0
    },
    {
      "activity": "gestureDetected",
      "state": "PinchDetected",
      "message": "Gesture detected not on slider",
      "cursor_X": 808.5991,
      "cursor_y": 721.7869,
      "slider_position_X": 600.0,
      "slider_value": 0
    },
    {
      "activity": "drawCalled",
      "state": "PinchDetected",
      "cursor_X": 808.5931,
      "cursor_y": 721.7865,
      "slider_position_X": 600.0,
      "slider_value": 0
    },
    {
      "activity": "gestureDetected",
      "state": "PinchDetected",
      "message": "Gesture detected not on slider",
      "cursor_X": 808.5931,
      "cursor_y": 721.7865,
      "slider_position_X": 600.0,
      "slider_value": 0
    },
    {
      "activity": "drawCalled",
      "state": "PinchDetected",
      "cursor_X": 808.57886,
      "cursor_y": 721.7859,
      "slider_position_X": 600.0,
      "slider_value": 0
    },
    {
      "activity": "gestureDetected",
      "state": "PinchDetected",
      "message": "Gesture detected not on slider",
      "cursor_X": 808.57886,
      "cursor_y": 721.7859,
      "slider_position_X": 600.0,
      "slider_value": 0
    },
    {
      "activity": "drawCalled",
      "state": "PinchDetected",
      "cursor_X": 808.5578,
      "cursor_y": 721.7852,
      "slider_position_X": 600.0,
      "slider_value": 0
    },
    {
      "activity": "gestureDetected",
      "state": "PinchDetected",
      "message": "Gesture detected not on slider",
      "cursor_X": 808.5578,
      "cursor_y": 721.7852,
      "slider_position_X": 600.0,
      "slider_value": 0
    },
    {
      "activity": "drawCalled",
      "state": "PinchDetected",
      "cursor_X": 808.4757,
      "cursor_y": 721.78284,
      "slider_position_X": 600.0,
      "slider_value": 0
    },
    {
      "activity": "gestureDetected",
      "state": "PinchDetected",
      "message": "Gesture detected not on slider",
      "cursor_X": 808.4757,
      "cursor_y": 721.78284,
      "slider_position_X": 600.0,
      "slider_value": 0
    },
    {
      "activity": "drawCalled",
      "state": "PinchDetected",
      "cursor_X": 808.42255,
      "cursor_y": 721.7813,
      "slider_position_X": 600.0,
      "slider_value": 0
    },
    {
      "activity": "gestureDetected",
      "state": "PinchDetected",
      "message": "Gesture detected not on slider",
      "cursor_X": 808.42255,
      "cursor_y": 721.7813,
      "slider_position_X": 600.0,
      "slider_value": 0
    },
    {
      "activity": "drawCalled",
      "state": "PinchDetected",
      "cursor_X": 808.1173,
      "cursor_y": 721.7729,
      "slider_position_X": 600.0,
      "slider_value": 0
    },
    {
      "activity": "gestureDetected",
      "state": "PinchDetected",
      "message": "Gesture detected not on slider",
      "cursor_X": 808.1173,
      "cursor_y": 721.7729,
      "slider_position_X": 600.0,
      "slider_value": 0
    },
    {
      "activity": "drawCalled",
      "state": "PinchDetected",
      "cursor_X": 807.74725,
      "cursor_y": 721.76044,
      "slider_position_X": 600.0,
      "slider_value": 0
    },
    {
      "activity": "gestureDetected",
      "state": "PinchDetected",
      "message": "Gesture detected not on slider",
      "cursor_X": 807.74725,
      "cursor_y": 721.76044,
      "slider_position_X": 600.0,
      "slider_value": 0
    },
    {
      "activity": "drawCalled",
      "state": "PinchDetected",
      "cursor_X": 807.74725,
      "cursor_y": 721.76044,
      "slider_position_X": 600.0,
      "slider_value": 0
    },
    {
      "activity": "gestureDetected",
      "state": "PinchDetected",
      "message": "Gesture detected not on slider",
      "cursor_X": 807.74725,
      "cursor_y": 721.76044,
      "slider_position_X": 600.0,
      "slider_value": 0
    },
    {
      "activity": "drawCalled",
      "state": "PinchDetected",
      "cursor_X": 805.5155,
      "cursor_y": 721.6792,
      "slider_position_X": 600.0,
      "slider_value": 0
    },
    {
      "activity": "gestureDetected",
      "state": "PinchDetected",
      "message": "Gesture detected not on slider",
      "cursor_X": 805.5155,
      "cursor_y": 721.6792,
      "slider_position_X": 600.0,
      "slider_value": 0
    },
    {
      "activity": "drawCalled",
      "state": "PinchDetected",
      "cursor_X": 803.21796,
      "cursor_y": 721.5886,
      "slider_position_X": 600.0,
      "slider_value": 0
    },
    {
      "activity": "gestureDetected",
      "state": "PinchDetected",
      "message": "Gesture detected not on slider",
      "cursor_X": 803.21796,
      "cursor_y": 721.5886,
      "slider_position_X": 600.0,
      "slider_value": 0
    },
    {
      "activity": "drawCalled",
      "state": "PinchDetected",
      "cursor_X": 799.1096,
      "cursor_y": 721.42535,
      "slider_position_X": 600.0,
      "slider_value": 0
    },
    {
      "activity": "gestureDetected",
      "state": "PinchDetected",
      "message": "Gesture detected not on slider",
      "cursor_X": 799.1096,
      "cursor_y": 721.42535,
      "slider_position_X": 600.0,
      "slider_value": 0
    },
    {
      "activity": "drawCalled",
      "state": "PinchDetected",
      "cursor_X": 792.1311,
      "cursor_y": 721.12805,
      "slider_position_X": 600.0,
      "slider_value": 0
    },
    {
      "activity": "gestureDetected",
      "state": "PinchDetected",
      "message": "Gesture detected not on slider",
      "cursor_X": 792.1311,
      "cursor_y": 721.12805,
      "slider_position_X": 600.0,
      "slider_value": 0
    },
    {
      "activity": "drawCalled",
      "state": "PinchDetected",
      "cursor_X": 775.2649,
      "cursor_y": 720.3638,
      "slider_position_X": 600.0,
      "slider_value": 0
    },
    {
      "activity": "gestureDetected",
      "state": "PinchDetected",
      "message": "Gesture detected not on slider",
      "cursor_X": 775.2649,
      "cursor_y": 720.3638,
      "slider_position_X": 600.0,
      "slider_value": 0
    },
    {
      "activity": "drawCalled",
      "state": "PinchDetected",
      "cursor_X": 760.36554,
      "cursor_y": 719.6939,
      "slider_position_X": 600.0,
      "slider_value": 0
    },
    {
      "activity": "gestureDetected",
      "state": "PinchDetected",
      "message": "Gesture detected not on slider",
      "cursor_X": 760.36554,
      "cursor_y": 719.6939,
      "slider_position_X": 600.0,
      "slider_value": 0
    },
    {
      "activity": "drawCalled",
      "state": "PinchDetected",
      "cursor_X": 742.7949,
      "cursor_y": 718.92096,
      "slider_position_X": 600.0,
      "slider_value": 0
    },
    {
      "activity": "gestureDetected",
      "state": "PinchDetected",
      "message": "Gesture detected not on slider",
      "cursor_X": 742.7949,
      "cursor_y": 718.92096,
      "slider_position_X": 600.0,
      "slider_value": 0
    },
    {
      "activity": "drawCalled",
      "state": "PinchDetected",
      "cursor_X": 722.75275,
      "cursor_y": 718.11414,
      "slider_position_X": 600.0,
      "slider_value": 0
    },
    {
      "activity": "gestureDetected",
      "state": "PinchDetected",
      "message": "Gesture detected not on slider",
      "cursor_X": 722.75275,
      "cursor_y": 718.11414,
      "slider_position_X": 600.0,
      "slider_value": 0
    },
    {
      "activity": "drawCalled",
      "state": "PinchDetected",
      "cursor_X": 701.03094,
      "cursor_y": 717.32904,
      "slider_position_X": 600.0,
      "slider_value": 0
    },
    {
      "activity": "gestureDetected",
      "state": "PinchDetected",
      "message": "Gesture detected not on slider",
      "cursor_X": 701.03094,
      "cursor_y": 717.32904,
      "slider_position_X": 600.0,
      "slider_value": 0
    },
    {
      "activity": "drawCalled",
      "state": "PinchDetected",
      "cursor_X": 678.7409,
      "cursor_y": 716.5585,
      "slider_position_X": 600.0,
      "slider_value": 0
    },
    {
      "activity": "gestureDetected",
      "state": "PinchDetected",
      "message": "Gesture detected not on slider",
      "cursor_X": 678.7409,
      "cursor_y": 716.5585,
      "slider_position_X": 600.0,
      "slider_value": 0
    },
    {
      "activity": "drawCalled",
      "state": "PinchDetected",
      "cursor_X": 657.15247,
      "cursor_y": 715.9317,
      "slider_position_X": 600.0,
      "slider_value": 0
    },
    {
      "activity": "gestureDetected",
      "state": "PinchDetected",
      "message": "Gesture detected not on slider",
      "cursor_X": 657.15247,
      "cursor_y": 715.9317,
      "slider_position_X": 600.0,
      "slider_value": 0
    },
    {
      "activity": "drawCalled",
      "state": "PinchDetected",
      "cursor_X": 637.1296,
      "cursor_y": 715.5381,
      "slider_position_X": 600.0,
      "slider_value": 0
    },
    {
      "activity": "sliderMoved",
      "state": "PinchDetected",
      "message": "Gesture detected on slider",
      "cursor_X": 637.1296,
      "cursor_y": 715.5381,
      "slider_position_X": 637.1296,
      "slider_value": 0
    },
    {
      "activity": "drawCalled",
      "state": "PinchDetected",
      "cursor_X": 619.31854,
      "cursor_y": 715.37054,
      "slider_position_X": 637.1296,
      "slider_value": 0
    },
    {
      "activity": "sliderMoved",
      "state": "PinchDetected",
      "message": "Gesture detected on slider",
      "cursor_X": 619.31854,
      "cursor_y": 715.37054,
      "slider_position_X": 619.31854,
      "slider_value": 0
    },
    {
      "activity": "drawCalled",
      "state": "PinchDetected",
      "cursor_X": 603.84064,
      "cursor_y": 715.39606,
      "slider_position_X": 619.31854,
      "slider_value": 0
    },
    {
      "activity": "sliderMoved",
      "state": "PinchDetected",
      "message": "Gesture detected on slider",
      "cursor_X": 603.84064,
      "cursor_y": 715.39606,
      "slider_position_X": 603.84064,
      "slider_value": 0
    },
    {
      "activity": "drawCalled",
      "state": "PinchDetected",
      "cursor_X": 590.78577,
      "cursor_y": 715.6169,
      "slider_position_X": 603.84064,
      "slider_value": 0
    },
    {
      "activity": "sliderMoved",
      "state": "PinchDetected",
      "message": "Gesture detected on slider",
      "cursor_X": 590.78577,
      "cursor_y": 715.6169,
      "slider_position_X": 600.0,
      "slider_value": 0
    },
    {
      "activity": "drawCalled",
      "state": "PinchDetected",
      "cursor_X": 579.88007,
      "cursor_y": 715.94183,
      "slider_position_X": 600.0,
      "slider_value": 0
    },
    {
      "activity": "sliderMoved",
      "state": "PinchDetected",
      "message": "Gesture detected on slider",
      "cursor_X": 579.88007,
      "cursor_y": 715.94183,
      "slider_position_X": 600.0,
      "slider_value": 0
    },
    {
      "activity": "drawCalled",
      "state": "PinchDetected",
      "cursor_X": 570.9997,
      "cursor_y": 716.36865,
      "slider_position_X": 600.0,
      "slider_value": 0
    },
    {
      "activity": "sliderMoved",
      "state": "PinchDetected",
      "message": "Gesture detected on slider",
      "cursor_X": 570.9997,
      "cursor_y": 716.36865,
      "slider_position_X": 600.0,
      "slider_value": 0
    },
    {
      "activity": "drawCalled",
      "state": "PinchDetected",
      "cursor_X": 561.55975,
      "cursor_y": 716.96564,
      "slider_position_X": 600.0,
      "slider_value": 0
    },
    {
      "activity": "sliderMoved",
      "state": "PinchDetected",
      "message": "Gesture continued away from slider",
      "cursor_X": 561.55975,
      "cursor_y": 716.96564,
      "slider_position_X": 600.0,
      "slider_value": 0
    },
    {
      "activity": "drawCalled",
      "state": "PinchDetected",
      "cursor_X": 557.4808,
      "cursor_y": 717.287,
      "slider_position_X": 600.0,
      "slider_value": 0
    },
    {
      "activity": "sliderMoved",
      "state": "PinchDetected",
      "message": "Gesture continued away from slider",
      "cursor_X": 557.4808,
      "cursor_y": 717.287,
      "slider_position_X": 600.0,
      "slider_value": 0
    },
    {
      "activity": "drawCalled",
      "state": "PinchDetected",
      "cursor_X": 554.8639,
      "cursor_y": 717.5468,
      "slider_position_X": 600.0,
      "slider_value": 0
    },
    {
      "activity": "sliderMoved",
      "state": "PinchDetected",
      "message": "Gesture continued away from slider",
      "cursor_X": 554.8639,
      "cursor_y": 717.5468,
      "slider_position_X": 600.0,
      "slider_value": 0
    },
    {
      "activity": "drawCalled",
      "state": "PinchDetected",
      "cursor_X": 553.186,
      "cursor_y": 717.7465,
      "slider_position_X": 600.0,
      "slider_value": 0
    },
    {
      "activity": "sliderMoved",
      "state": "PinchDetected",
      "message": "Gesture continued away from slider",
      "cursor_X": 553.186,
      "cursor_y": 717.7465,
      "slider_position_X": 600.0,
      "slider_value": 0
    },
    {
      "activity": "drawCalled",
      "state": "PinchDetected",
      "cursor_X": 552.10175,
      "cursor_y": 717.89374,
      "slider_position_X": 600.0,
      "slider_value": 0
    },
    {
      "activity": "sliderMoved",
      "state": "PinchDetected",
      "message": "Gesture continued away from slider",
      "cursor_X": 552.10175,
      "cursor_y": 717.89374,
      "slider_position_X": 600.0,
      "slider_value": 0
    },
    {
      "activity": "drawCalled",
      "state": "PinchDetected",
      "cursor_X": 551.3797,
      "cursor_y": 718.0174,
      "slider_position_X": 600.0,
      "slider_value": 0
    },
    {
      "activity": "sliderMoved",
      "state": "PinchDetected",
      "message": "Gesture continued away from slider",
      "cursor_X": 551.3797,
      "cursor_y": 718.0174,
      "slider_position_X": 600.0,
      "slider_value": 0
    },
    {
      "activity": "drawCalled",
      "state": "PinchDetected",
      "cursor_X": 550.8679,
      "cursor_y": 718.1268,
      "slider_position_X": 600.0,
      "slider_value": 0
    },
    {
      "activity": "sliderMoved",
      "state": "PinchDetected",
      "message": "Gesture continued away from slider",
      "cursor_X": 550.66675,
      "cursor_y": 718.1767,
      "slider_position_X": 600.0,
      "slider_value": 0
    },
    {
      "activity": "drawCalled",
      "state": "PinchDetected",
      "cursor_X": 550.3583,
      "cursor_y": 718.2576,
      "slider_position_X": 600.0,
      "slider_value": 0
    },
    {
      "activity": "sliderMoved",
      "state": "PinchDetected",
      "message": "Gesture continued away from slider",
      "cursor_X": 550.3583,
      "cursor_y": 718.2576,
      "slider_position_X": 600.0,
      "slider_value": 0
    },
    {
      "activity": "drawCalled",
      "state": "PinchDetected",
      "cursor_X": 550.17487,
      "cursor_y": 718.30664,
      "slider_position_X": 600.0,
      "slider_value": 0
    },
    {
      "activity": "sliderMoved",
      "state": "PinchDetected",
      "message": "Gesture continued away from slider",
      "cursor_X": 550.17487,
      "cursor_y": 718.30664,
      "slider_position_X": 600.0,
      "slider_value": 0
    },
    {
      "activity": "drawCalled",
      "state": "PinchDetected",
      "cursor_X": 550.06537,
      "cursor_y": 718.33954,
      "slider_position_X": 600.0,
      "slider_value": 0
    },
    {
      "activity": "sliderMoved",
      "state": "PinchDetected",
      "message": "Gesture continued away from slider",
      "cursor_X": 550.06537,
      "cursor_y": 718.33954,
      "slider_position_X": 600.0,
      "slider_value": 0
    },
    {
      "activity": "drawCalled",
      "state": "PinchDetected",
      "cursor_X": 550.0029,
      "cursor_y": 718.3598,
      "slider_position_X": 600.0,
      "slider_value": 0
    },
    {
      "activity": "sliderMoved",
      "state": "PinchDetected",
      "message": "Gesture continued away from slider",
      "cursor_X": 550.0029,
      "cursor_y": 718.3598,
      "slider_position_X": 600.0,
      "slider_value": 0
    },
    {
      "activity": "drawCalled",
      "state": "PinchDetected",
      "cursor_X": 549.96875,
      "cursor_y": 718.3715,
      "slider_position_X": 600.0,
      "slider_value": 0
    },
    {
      "activity": "sliderMoved",
      "state": "PinchDetected",
      "message": "Gesture continued away from slider",
      "cursor_X": 549.96875,
      "cursor_y": 718.3715,
      "slider_position_X": 600.0,
      "slider_value": 0
    },
    {
      "activity": "drawCalled",
      "state": "PinchDetected",
      "cursor_X": 549.9493,
      "cursor_y": 718.379,
      "slider_position_X": 600.0,
      "slider_value": 0
    },
    {
      "activity": "sliderMoved",
      "state": "PinchDetected",
      "message": "Gesture continued away from slider",
      "cursor_X": 549.9493,
      "cursor_y": 718.379,
      "slider_position_X": 600.0,
      "slider_value": 0
    },
    {
      "activity": "drawCalled",
      "state": "PinchDetected",
      "cursor_X": 549.93774,
      "cursor_y": 718.3838,
      "slider_position_X": 600.0,
      "slider_value": 0
    },
    {
      "activity": "sliderMoved",
      "state": "PinchDetected",
      "message": "Gesture continued away from slider",
      "cursor_X": 549.93774,
      "cursor_y": 718.3838,
      "slider_position_X": 600.0,
      "slider_value": 0
    },
    {
      "activity": "drawCalled",
      "state": "PinchDetected",
      "cursor_X": 549.92944,
      "cursor_y": 718.3882,
      "slider_position_X": 600.0,
      "slider_value": 0
    },
    {
      "activity": "sliderMoved",
      "state": "PinchDetected",
      "message": "Gesture continued away from slider",
      "cursor_X": 549.92944,
      "cursor_y": 718.3882,
      "slider_position_X": 600.0,
      "slider_value": 0
    },
    {
      "activity": "drawCalled",
      "state": "PinchDetected",
      "cursor_X": 549.92303,
      "cursor_y": 718.3918,
      "slider_position_X": 600.0,
      "slider_value": 0
    },
    {
      "activity": "sliderMoved",
      "state": "PinchDetected",
      "message": "Gesture continued away from slider",
      "cursor_X": 549.92303,
      "cursor_y": 718.3918,
      "slider_position_X": 600.0,
      "slider_value": 0
    },
    {
      "activity": "drawCalled",
      "state": "PinchDetected",
      "cursor_X": 549.9194,
      "cursor_y": 718.39404,
      "slider_position_X": 600.0,
      "slider_value": 0
    },
    {
      "activity": "sliderMoved",
      "state": "PinchDetected",
      "message": "Gesture continued away from slider",
      "cursor_X": 549.9194,
      "cursor_y": 718.39404,
      "slider_position_X": 600.0,
      "slider_value": 0
    },
    {
      "activity": "drawCalled",
      "state": "PinchDetected",
      "cursor_X": 549.91736,
      "cursor_y": 718.39514,
      "slider_position_X": 600.0,
      "slider_value": 0
    },
    {
      "activity": "sliderMoved",
      "state": "PinchDetected",
      "message": "Gesture continued away from slider",
      "cursor_X": 549.91736,
      "cursor_y": 718.39514,
      "slider_position_X": 600.0,
      "slider_value": 0
    },
    {
      "activity": "drawCalled",
      "state": "PinchDetected",
      "cursor_X": 549.91547,
      "cursor_y": 718.39667,
      "slider_position_X": 600.0,
      "slider_value": 0
    },
    {
      "activity": "sliderMoved",
      "state": "PinchDetected",
      "message": "Gesture continued away from slider",
      "cursor_X": 549.91547,
      "cursor_y": 718.39667,
      "slider_position_X": 600.0,
      "slider_value": 0
    },
    {
      "activity": "drawCalled",
      "state": "PinchDetected",
      "cursor_X": 549.91425,
      "cursor_y": 718.3979,
      "slider_position_X": 600.0,
      "slider_value": 0
    },
    {
      "activity": "sliderMoved",
      "state": "PinchDetected",
      "message": "Gesture continued away from slider",
      "cursor_X": 549.91425,
      "cursor_y": 718.3979,
      "slider_position_X": 600.0,
      "slider_value": 0
    },
    {
      "activity": "drawCalled",
      "state": "PinchDetected",
      "cursor_X": 549.913,
      "cursor_y": 718.3996,
      "slider_position_X": 600.0,
      "slider_value": 0
    },
    {
      "activity": "sliderMoved",
      "state": "PinchDetected",
      "message": "Gesture continued away from slider",
      "cursor_X": 549.913,
      "cursor_y": 718.3996,
      "slider_position_X": 600.0,
      "slider_value": 0
    },
    {
      "activity": "drawCalled",
      "state": "PinchDetected",
      "cursor_X": 549.9116,
      "cursor_y": 718.4026,
      "slider_position_X": 600.0,
      "slider_value": 0
    },
    {
      "activity": "sliderMoved",
      "state": "PinchDetected",
      "message": "Gesture continued away from slider",
      "cursor_X": 549.9116,
      "cursor_y": 718.4026,
      "slider_position_X": 600.0,
      "slider_value": 0
    },
    {
      "activity": "drawCalled",
      "state": "PinchDetected",
      "cursor_X": 549.91016,
      "cursor_y": 718.4075,
      "slider_position_X": 600.0,
      "slider_value": 0
    },
    {
      "activity": "sliderMoved",
      "state": "PinchDetected",
      "message": "Gesture continued away from slider",
      "cursor_X": 549.91016,
      "cursor_y": 718.4075,
      "slider_position_X": 600.0,
      "slider_value": 0
    },
    {
      "activity": "drawCalled",
      "state": "PinchDetected",
      "cursor_X": 549.90875,
      "cursor_y": 718.41315,
      "slider_position_X": 600.0,
      "slider_value": 0
    },
    {
      "activity": "sliderMoved",
      "state": "PinchDetected",
      "message": "Gesture continued away from slider",
      "cursor_X": 549.90875,
      "cursor_y": 718.41315,
      "slider_position_X": 600.0,
      "slider_value": 0
    },
    {
      "activity": "drawCalled",
      "state": "PinchDetected",
      "cursor_X": 549.90784,
      "cursor_y": 718.4186,
      "slider_position_X": 600.0,
      "slider_value": 0
    },
    {
      "activity": "sliderMoved",
      "state": "PinchDetected",
      "message": "Gesture continued away from slider",
      "cursor_X": 549.90784,
      "cursor_y": 718.4186,
      "slider_position_X": 600.0,
      "slider_value": 0
    },
    {
      "activity": "drawCalled",
      "state": "PinchDetected",
      "cursor_X": 549.90735,
      "cursor_y": 718.42365,
      "slider_position_X": 600.0,
      "slider_value": 0
    },
    {
      "activity": "sliderMoved",
      "state": "PinchDetected",
      "message": "Gesture continued away from slider",
      "cursor_X": 549.90735,
      "cursor_y": 718.42365,
      "slider_position_X": 600.0,
      "slider_value": 0
    },
    {
      "activity": "drawCalled",
      "state": "PinchDetected",
      "cursor_X": 549.9077,
      "cursor_y": 718.42957,
      "slider_position_X": 600.0,
      "slider_value": 0
    },
    {
      "activity": "sliderMoved",
      "state": "PinchDetected",
      "message": "Gesture continued away from slider",
      "cursor_X": 549.9077,
      "cursor_y": 718.42957,
      "slider_position_X": 600.0,
      "slider_value": 0
    },
    {
      "activity": "drawCalled",
      "state": "PinchDetected",
      "cursor_X": 549.91284,
      "cursor_y": 718.44604,
      "slider_position_X": 600.0,
      "slider_value": 0
    },
    {
      "activity": "sliderMoved",
      "state": "PinchDetected",
      "message": "Gesture continued away from slider",
      "cursor_X": 549.91284,
      "cursor_y": 718.44604,
      "slider_position_X": 600.0,
      "slider_value": 0
    },
    {
      "activity": "drawCalled",
      "state": "PinchDetected",
      "cursor_X": 549.9212,
      "cursor_y": 718.46277,
      "slider_position_X": 600.0,
      "slider_value": 0
    },
    {
      "activity": "sliderMoved",
      "state": "PinchDetected",
      "message": "Gesture continued away from slider",
      "cursor_X": 549.9212,
      "cursor_y": 718.46277,
      "slider_position_X": 600.0,
      "slider_value": 0
    },
    {
      "activity": "drawCalled",
      "state": "PinchDetected",
      "cursor_X": 549.934,
      "cursor_y": 718.483,
      "slider_position_X": 600.0,
      "slider_value": 0
    },
    {
      "activity": "sliderMoved",
      "state": "PinchDetected",
      "message": "Gesture continued away from slider",
      "cursor_X": 549.934,
      "cursor_y": 718.483,
      "slider_position_X": 600.0,
      "slider_value": 0
    },
    {
      "activity": "drawCalled",
      "state": "PinchDetected",
      "cursor_X": 549.9689,
      "cursor_y": 718.5259,
      "slider_position_X": 600.0,
      "slider_value": 0
    },
    {
      "activity": "sliderMoved",
      "state": "PinchDetected",
      "message": "Gesture continued away from slider",
      "cursor_X": 549.9689,
      "cursor_y": 718.5259,
      "slider_position_X": 600.0,
      "slider_value": 0
    },
    {
      "activity": "drawCalled",
      "state": "PinchDetected",
      "cursor_X": 550.0055,
      "cursor_y": 718.56165,
      "slider_position_X": 600.0,
      "slider_value": 0
    },
    {
      "activity": "sliderMoved",
      "state": "PinchDetected",
      "message": "Gesture continued away from slider",
      "cursor_X": 550.0115,
      "cursor_y": 718.5669,
      "slider_position_X": 600.0,
      "slider_value": 0
    },
    {
      "activity": "drawCalled",
      "state": "PinchDetected",
      "cursor_X": 550.0288,
      "cursor_y": 718.5815,
      "slider_position_X": 600.0,
      "slider_value": 0
    },
    {
      "activity": "sliderMoved",
      "state": "PinchDetected",
      "message": "Gesture continued away from slider",
      "cursor_X": 550.0288,
      "cursor_y": 718.5815,
      "slider_position_X": 600.0,
      "slider_value": 0
    },
    {
      "activity": "drawCalled",
      "state": "PinchDetected",
      "cursor_X": 550.0369,
      "cursor_y": 718.5881,
      "slider_position_X": 600.0,
      "slider_value": 0
    },
    {
      "activity": "sliderMoved",
      "state": "PinchDetected",
      "message": "Gesture continued away from slider",
      "cursor_X": 550.0369,
      "cursor_y": 718.5881,
      "slider_position_X": 600.0,
      "slider_value": 0
    },
    {
      "activity": "drawCalled",
      "state": "PinchDetected",
      "cursor_X": 550.0432,
      "cursor_y": 718.5931,
      "slider_position_X": 600.0,
      "slider_value": 0
    },
    {
      "activity": "sliderMoved",
      "state": "PinchDetected",
      "message": "Gesture continued away from slider",
      "cursor_X": 550.0432,
      "cursor_y": 718.5931,
      "slider_position_X": 600.0,
      "slider_value": 0
    },
    {
      "activity": "drawCalled",
      "state": "PinchDetected",
      "cursor_X": 550.046,
      "cursor_y": 718.5953,
      "slider_position_X": 600.0,
      "slider_value": 0
    },
    {
      "activity": "sliderMoved",
      "state": "PinchDetected",
      "message": "Gesture continued away from slider",
      "cursor_X": 550.046,
      "cursor_y": 718.5953,
      "slider_position_X": 600.0,
      "slider_value": 0
    },
    {
      "activity": "drawCalled",
      "state": "PinchDetected",
      "cursor_X": 550.0481,
      "cursor_y": 718.5969,
      "slider_position_X": 600.0,
      "slider_value": 0
    },
    {
      "activity": "sliderMoved",
      "state": "PinchDetected",
      "message": "Gesture continued away from slider",
      "cursor_X": 550.0481,
      "cursor_y": 718.5969,
      "slider_position_X": 600.0,
      "slider_value": 0
    },
    {
      "activity": "drawCalled",
      "state": "PinchDetected",
      "cursor_X": 550.0481,
      "cursor_y": 718.5969,
      "slider_position_X": 600.0,
      "slider_value": 0
    },
    {
      "activity": "sliderMoved",
      "state": "PinchDetected",
      "message": "Gesture continued away from slider",
      "cursor_X": 550.0481,
      "cursor_y": 718.5969,
      "slider_position_X": 600.0,
      "slider_value": 0
    },
    {
      "activity": "drawCalled",
      "state": "PinchDetected",
      "cursor_X": 550.05005,
      "cursor_y": 718.5986,
      "slider_position_X": 600.0,
      "slider_value": 0
    },
    {
      "activity": "sliderMoved",
      "state": "PinchDetected",
      "message": "Gesture continued away from slider",
      "cursor_X": 550.05005,
      "cursor_y": 718.5986,
      "slider_position_X": 600.0,
      "slider_value": 0
    },
    {
      "activity": "drawCalled",
      "state": "PinchDetected",
      "cursor_X": 550.05005,
      "cursor_y": 718.5986,
      "slider_position_X": 600.0,
      "slider_value": 0
    },
    {
      "activity": "sliderMoved",
      "state": "PinchDetected",
      "message": "Gesture continued away from slider",
      "cursor_X": 550.05005,
      "cursor_y": 718.5986,
      "slider_position_X": 600.0,
      "slider_value": 0
    },
    {
      "activity": "drawCalled",
      "state": "PinchDetected",
      "cursor_X": 550.05005,
      "cursor_y": 718.5986,
      "slider_position_X": 600.0,
      "slider_value": 0
    },
    {
      "activity": "sliderMoved",
      "state": "PinchDetected",
      "message": "Gesture continued away from slider",
      "cursor_X": 550.05005,
      "cursor_y": 718.5986,
      "slider_position_X": 600.0,
      "slider_value": 0
    },
    {
      "activity": "drawCalled",
      "state": "PinchDetected",
      "cursor_X": 550.0501,
      "cursor_y": 718.5986,
      "slider_position_X": 600.0,
      "slider_value": 0
    },
    {
      "activity": "sliderMoved",
      "state": "PinchDetected",
      "message": "Gesture continued away from slider",
      "cursor_X": 550.0501,
      "cursor_y": 718.5986,
      "slider_position_X": 600.0,
      "slider_value": 0
    },
    {
      "activity": "drawCalled",
      "state": "PinchDetected",
      "cursor_X": 550.0502,
      "cursor_y": 718.59863,
      "slider_position_X": 600.0,
      "slider_value": 0
    },
    {
      "activity": "sliderMoved",
      "state": "PinchDetected",
      "message": "Gesture continued away from slider",
      "cursor_X": 550.0502,
      "cursor_y": 718.59863,
      "slider_position_X": 600.0,
      "slider_value": 0
    },
    {
      "activity": "drawCalled",
      "state": "PinchDetected",
      "cursor_X": 550.05035,
      "cursor_y": 718.59875,
      "slider_position_X": 600.0,
      "slider_value": 0
    },
    {
      "activity": "sliderMoved",
      "state": "PinchDetected",
      "message": "Gesture continued away from slider",
      "cursor_X": 550.05035,
      "cursor_y": 718.59875,
      "slider_position_X": 600.0,
      "slider_value": 0
    },
    {
      "activity": "drawCalled",
      "state": "PinchDetected",
      "cursor_X": 550.0504,
      "cursor_y": 718.5988,
      "slider_position_X": 600.0,
      "slider_value": 0
    },
    {
      "activity": "sliderMoved",
      "state": "PinchDetected",
      "message": "Gesture continued away from slider",
      "cursor_X": 550.0504,
      "cursor_y": 718.5988,
      "slider_position_X": 600.0,
      "slider_value": 0
    },
    {
      "activity": "drawCalled",
      "state": "PinchDetected",
      "cursor_X": 550.05054,
      "cursor_y": 718.5989,
      "slider_position_X": 600.0,
      "slider_value": 0
    },
    {
      "activity": "sliderMoved",
      "state": "PinchDetected",
      "message": "Gesture continued away from slider",
      "cursor_X": 550.05054,
      "cursor_y": 718.5989,
      "slider_position_X": 600.0,
      "slider_value": 0
    },
    {
      "activity": "drawCalled",
      "state": "PinchDetected",
      "cursor_X": 550.05066,
      "cursor_y": 718.599,
      "slider_position_X": 600.0,
      "slider_value": 0
    },
    {
      "activity": "sliderMoved",
      "state": "PinchDetected",
      "message": "Gesture continued away from slider",
      "cursor_X": 550.05066,
      "cursor_y": 718.599,
      "slider_position_X": 600.0,
      "slider_value": 0
    },
    {
      "activity": "drawCalled",
      "state": "PinchDetected",
      "cursor_X": 550.05096,
      "cursor_y": 718.5992,
      "slider_position_X": 600.0,
      "slider_value": 0
    },
    {
      "activity": "sliderMoved",
      "state": "PinchDetected",
      "message": "Gesture continued away from slider",
      "cursor_X": 550.05096,
      "cursor_y": 718.5992,
      "slider_position_X": 600.0,
      "slider_value": 0
    },
    {
      "activity": "drawCalled",
      "state": "PinchDetected",
      "cursor_X": 550.052,
      "cursor_y": 718.59985,
      "slider_position_X": 600.0,
      "slider_value": 0
    },
    {
      "activity": "sliderMoved",
      "state": "PinchDetected",
      "message": "Gesture continued away from slider",
      "cursor_X": 550.052,
      "cursor_y": 718.59985,
      "slider_position_X": 600.0,
      "slider_value": 0
    },
    {
      "activity": "drawCalled",
      "state": "PinchDetected",
      "cursor_X": 550.0592,
      "cursor_y": 718.60425,
      "slider_position_X": 600.0,
      "slider_value": 0
    },
    {
      "activity": "sliderMoved",
      "state": "PinchDetected",
      "message": "Gesture continued away from slider",
      "cursor_X": 550.0592,
      "cursor_y": 718.60425,
      "slider_position_X": 600.0,
      "slider_value": 0
    },
    {
      "activity": "drawCalled",
      "state": "PinchDetected",
      "cursor_X": 550.103,
      "cursor_y": 718.6303,
      "slider_position_X": 600.0,
      "slider_value": 0
    },
    {
      "activity": "sliderMoved",
      "state": "PinchDetected",
      "message": "Gesture continued away from slider",
      "cursor_X": 550.103,
      "cursor_y": 718.6303,
      "slider_position_X": 600.0,
      "slider_value": 0
    },
    {
      "activity": "drawCalled",
      "state": "PinchDetected",
      "cursor_X": 550.30945,
      "cursor_y": 718.74866,
      "slider_position_X": 600.0,
      "slider_value": 0
    },
    {
      "activity": "sliderMoved",
      "state": "PinchDetected",
      "message": "Gesture continued away from slider",
      "cursor_X": 550.30945,
      "cursor_y": 718.74866,
      "slider_position_X": 600.0,
      "slider_value": 0
    },
    {
      "activity": "drawCalled",
      "state": "PinchDetected",
      "cursor_X": 550.9772,
      "cursor_y": 719.1139,
      "slider_position_X": 600.0,
      "slider_value": 0
    },
    {
      "activity": "sliderMoved",
      "state": "PinchDetected",
      "message": "Gesture continued away from slider",
      "cursor_X": 550.9772,
      "cursor_y": 719.1139,
      "slider_position_X": 600.0,
      "slider_value": 0
    },
    {
      "activity": "drawCalled",
      "state": "PinchDetected",
      "cursor_X": 552.621,
      "cursor_y": 719.967,
      "slider_position_X": 600.0,
      "slider_value": 0
    },
    {
      "activity": "sliderMoved",
      "state": "PinchDetected",
      "message": "Gesture continued away from slider",
      "cursor_X": 552.621,
      "cursor_y": 719.967,
      "slider_position_X": 600.0,
      "slider_value": 0
    },
    {
      "activity": "drawCalled",
      "state": "PinchDetected",
      "cursor_X": 558.807,
      "cursor_y": 722.9427,
      "slider_position_X": 600.0,
      "slider_value": 0
    },
    {
      "activity": "sliderMoved",
      "state": "PinchDetected",
      "message": "Gesture continued away from slider",
      "cursor_X": 558.807,
      "cursor_y": 722.9427,
      "slider_position_X": 600.0,
      "slider_value": 0
    },
    {
      "activity": "drawCalled",
      "state": "PinchDetected",
      "cursor_X": 566.0806,
      "cursor_y": 726.1929,
      "slider_position_X": 600.0,
      "slider_value": 0
    },
    {
      "activity": "sliderMoved",
      "state": "PinchDetected",
      "message": "Gesture detected on slider",
      "cursor_X": 566.0806,
      "cursor_y": 726.1929,
      "slider_position_X": 600.0,
      "slider_value": 0
    },
    {
      "activity": "drawCalled",
      "state": "PinchDetected",
      "cursor_X": 577.9139,
      "cursor_y": 731.01404,
      "slider_position_X": 600.0,
      "slider_value": 0
    },
    {
      "activity": "sliderMoved",
      "state": "PinchDetected",
      "message": "Gesture detected on slider",
      "cursor_X": 577.9139,
      "cursor_y": 731.01404,
      "slider_position_X": 600.0,
      "slider_value": 0
    },
    {
      "activity": "drawCalled",
      "state": "PinchDetected",
      "cursor_X": 593.33124,
      "cursor_y": 736.8462,
      "slider_position_X": 600.0,
      "slider_value": 0
    },
    {
      "activity": "sliderMoved",
      "state": "PinchDetected",
      "message": "Gesture detected on slider",
      "cursor_X": 593.33124,
      "cursor_y": 736.8462,
      "slider_position_X": 600.0,
      "slider_value": 0
    },
    {
      "activity": "drawCalled",
      "state": "PinchDetected",
      "cursor_X": 608.7461,
      "cursor_y": 742.3262,
      "slider_position_X": 600.0,
      "slider_value": 0
    },
    {
      "activity": "sliderMoved",
      "state": "PinchDetected",
      "message": "Gesture detected on slider",
      "cursor_X": 608.7461,
      "cursor_y": 742.3262,
      "slider_position_X": 608.7461,
      "slider_value": 0
    },
    {
      "activity": "drawCalled",
      "state": "PinchDetected",
      "cursor_X": 621.2353,
      "cursor_y": 746.55707,
      "slider_position_X": 608.7461,
      "slider_value": 0
    },
    {
      "activity": "sliderMoved",
      "state": "PinchDetected",
      "message": "Gesture detected on slider",
      "cursor_X": 621.2353,
      "cursor_y": 746.55707,
      "slider_position_X": 621.2353,
      "slider_value": 0
    },
    {
      "activity": "drawCalled",
      "state": "PinchDetected",
      "cursor_X": 629.9108,
      "cursor_y": 749.38477,
      "slider_position_X": 621.2353,
      "slider_value": 0
    },
    {
      "activity": "sliderMoved",
      "state": "PinchDetected",
      "message": "Gesture detected on slider",
      "cursor_X": 629.9108,
      "cursor_y": 749.38477,
      "slider_position_X": 629.9108,
      "slider_value": 0
    },
    {
      "activity": "drawCalled",
      "state": "PinchDetected",
      "cursor_X": 635.71625,
      "cursor_y": 751.20734,
      "slider_position_X": 629.9108,
      "slider_value": 0
    },
    {
      "activity": "sliderMoved",
      "state": "PinchDetected",
      "message": "Gesture detected on slider",
      "cursor_X": 635.71625,
      "cursor_y": 751.20734,
      "slider_position_X": 635.71625,
      "slider_value": 0
    },
    {
      "activity": "drawCalled",
      "state": "PinchDetected",
      "cursor_X": 639.40894,
      "cursor_y": 752.30664,
      "slider_position_X": 635.71625,
      "slider_value": 0
    },
    {
      "activity": "sliderMoved",
      "state": "PinchDetected",
      "message": "Gesture detected on slider",
      "cursor_X": 639.40894,
      "cursor_y": 752.30664,
      "slider_position_X": 639.40894,
      "slider_value": 0
    },
    {
      "activity": "drawCalled",
      "state": "PinchDetected",
      "cursor_X": 642.0444,
      "cursor_y": 753.0323,
      "slider_position_X": 639.40894,
      "slider_value": 0
    },
    {
      "activity": "sliderMoved",
      "state": "PinchDetected",
      "message": "Gesture detected on slider",
      "cursor_X": 643.02295,
      "cursor_y": 753.28955,
      "slider_position_X": 642.0444,
      "slider_value": 0
    },
    {
      "activity": "drawCalled",
      "state": "PinchDetected",
      "cursor_X": 644.41077,
      "cursor_y": 753.6373,
      "slider_position_X": 642.0444,
      "slider_value": 0
    },
    {
      "activity": "sliderMoved",
      "state": "PinchDetected",
      "message": "Gesture detected on slider",
      "cursor_X": 644.41077,
      "cursor_y": 753.6373,
      "slider_position_X": 644.41077,
      "slider_value": 0
    },
    {
      "activity": "drawCalled",
      "state": "PinchDetected",
      "cursor_X": 645.27966,
      "cursor_y": 753.83984,
      "slider_position_X": 644.41077,
      "slider_value": 0
    },
    {
      "activity": "sliderMoved",
      "state": "PinchDetected",
      "message": "Gesture detected on slider",
      "cursor_X": 645.27966,
      "cursor_y": 753.83984,
      "slider_position_X": 645.27966,
      "slider_value": 0
    },
    {
      "activity": "drawCalled",
      "state": "PinchDetected",
      "cursor_X": 645.7814,
      "cursor_y": 753.9491,
      "slider_position_X": 645.27966,
      "slider_value": 0
    },
    {
      "activity": "sliderMoved",
      "state": "PinchDetected",
      "message": "Gesture detected on slider",
      "cursor_X": 645.7814,
      "cursor_y": 753.9491,
      "slider_position_X": 645.7814,
      "slider_value": 0
    },
    {
      "activity": "drawCalled",
      "state": "PinchDetected",
      "cursor_X": 646.0751,
      "cursor_y": 754.00836,
      "slider_position_X": 645.7814,
      "slider_value": 0
    },
    {
      "activity": "sliderMoved",
      "state": "PinchDetected",
      "message": "Gesture detected on slider",
      "cursor_X": 646.0751,
      "cursor_y": 754.00836,
      "slider_position_X": 646.0751,
      "slider_value": 0
    },
    {
      "activity": "drawCalled",
      "state": "PinchDetected",
      "cursor_X": 646.2471,
      "cursor_y": 754.0408,
      "slider_position_X": 646.0751,
      "slider_value": 0
    },
    {
      "activity": "sliderMoved",
      "state": "PinchDetected",
      "message": "Gesture detected on slider",
      "cursor_X": 646.2471,
      "cursor_y": 754.0408,
      "slider_position_X": 646.2471,
      "slider_value": 0
    },
    {
      "activity": "drawCalled",
      "state": "PinchDetected",
      "cursor_X": 646.3469,
      "cursor_y": 754.0587,
      "slider_position_X": 646.2471,
      "slider_value": 0
    },
    {
      "activity": "sliderMoved",
      "state": "PinchDetected",
      "message": "Gesture detected on slider",
      "cursor_X": 646.3469,
      "cursor_y": 754.0587,
      "slider_position_X": 646.3469,
      "slider_value": 0
    },
    {
      "activity": "drawCalled",
      "state": "PinchDetected",
      "cursor_X": 646.4268,
      "cursor_y": 754.07227,
      "slider_position_X": 646.3469,
      "slider_value": 0
    },
    {
      "activity": "sliderMoved",
      "state": "PinchDetected",
      "message": "Gesture detected on slider",
      "cursor_X": 646.4268,
      "cursor_y": 754.07227,
      "slider_position_X": 646.4268,
      "slider_value": 0
    },
    {
      "activity": "drawCalled",
      "state": "PinchDetected",
      "cursor_X": 646.4533,
      "cursor_y": 754.07654,
      "slider_position_X": 646.4268,
      "slider_value": 0
    },
    {
      "activity": "sliderMoved",
      "state": "PinchDetected",
      "message": "Gesture detected on slider",
      "cursor_X": 646.4533,
      "cursor_y": 754.07654,
      "slider_position_X": 646.4533,
      "slider_value": 0
    },
    {
      "activity": "drawCalled",
      "state": "PinchDetected",
      "cursor_X": 646.4692,
      "cursor_y": 754.07904,
      "slider_position_X": 646.4533,
      "slider_value": 0
    },
    {
      "activity": "sliderMoved",
      "state": "PinchDetected",
      "message": "Gesture detected on slider",
      "cursor_X": 646.4692,
      "cursor_y": 754.07904,
      "slider_position_X": 646.4692,
      "slider_value": 0
    },
    {
      "activity": "drawCalled",
      "state": "PinchDetected",
      "cursor_X": 646.4796,
      "cursor_y": 754.08057,
      "slider_position_X": 646.4692,
      "slider_value": 0
    },
    {
      "activity": "sliderMoved",
      "state": "PinchDetected",
      "message": "Gesture detected on slider",
      "cursor_X": 646.4796,
      "cursor_y": 754.08057,
      "slider_position_X": 646.4796,
      "slider_value": 0
    },
    {
      "activity": "drawCalled",
      "state": "PinchDetected",
      "cursor_X": 646.4875,
      "cursor_y": 754.08167,
      "slider_position_X": 646.4796,
      "slider_value": 0
    },
    {
      "activity": "sliderMoved",
      "state": "PinchDetected",
      "message": "Gesture detected on slider",
      "cursor_X": 646.4875,
      "cursor_y": 754.08167,
      "slider_position_X": 646.4875,
      "slider_value": 0
    },
    {
      "activity": "drawCalled",
      "state": "PinchDetected",
      "cursor_X": 646.49646,
      "cursor_y": 754.0829,
      "slider_position_X": 646.4875,
      "slider_value": 0
    },
    {
      "activity": "sliderMoved",
      "state": "PinchDetected",
      "message": "Gesture detected on slider",
      "cursor_X": 646.49646,
      "cursor_y": 754.0829,
      "slider_position_X": 646.49646,
      "slider_value": 0
    },
    {
      "activity": "drawCalled",
      "state": "PinchDetected",
      "cursor_X": 646.5123,
      "cursor_y": 754.08484,
      "slider_position_X": 646.49646,
      "slider_value": 0
    },
    {
      "activity": "sliderMoved",
      "state": "PinchDetected",
      "message": "Gesture detected on slider",
      "cursor_X": 646.5123,
      "cursor_y": 754.08484,
      "slider_position_X": 646.5123,
      "slider_value": 0
    },
    {
      "activity": "drawCalled",
      "state": "PinchDetected",
      "cursor_X": 646.5424,
      "cursor_y": 754.0883,
      "slider_position_X": 646.5123,
      "slider_value": 0
    },
    {
      "activity": "sliderMoved",
      "state": "PinchDetected",
      "message": "Gesture detected on slider",
      "cursor_X": 646.5424,
      "cursor_y": 754.0883,
      "slider_position_X": 646.5424,
      "slider_value": 0
    },
    {
      "activity": "drawCalled",
      "state": "PinchDetected",
      "cursor_X": 646.7376,
      "cursor_y": 754.1087,
      "slider_position_X": 646.5424,
      "slider_value": 0
    },
    {
      "activity": "sliderMoved",
      "state": "PinchDetected",
      "message": "Gesture detected on slider",
      "cursor_X": 646.7376,
      "cursor_y": 754.1087,
      "slider_position_X": 646.7376,
      "slider_value": 0
    },
    {
      "activity": "drawCalled",
      "state": "PinchDetected",
      "cursor_X": 647.1992,
      "cursor_y": 754.1503,
      "slider_position_X": 646.7376,
      "slider_value": 0
    },
    {
      "activity": "sliderMoved",
      "state": "PinchDetected",
      "message": "Gesture detected on slider",
      "cursor_X": 647.1992,
      "cursor_y": 754.1503,
      "slider_position_X": 647.1992,
      "slider_value": 0
    },
    {
      "activity": "drawCalled",
      "state": "PinchDetected",
      "cursor_X": 647.9222,
      "cursor_y": 754.20447,
      "slider_position_X": 647.1992,
      "slider_value": 0
    },
    {
      "activity": "sliderMoved",
      "state": "PinchDetected",
      "message": "Gesture detected on slider",
      "cursor_X": 647.9222,
      "cursor_y": 754.20447,
      "slider_position_X": 647.9222,
      "slider_value": 0
    },
    {
      "activity": "drawCalled",
      "state": "PinchDetected",
      "cursor_X": 648.8122,
      "cursor_y": 754.2547,
      "slider_position_X": 647.9222,
      "slider_value": 0
    },
    {
      "activity": "sliderMoved",
      "state": "PinchDetected",
      "message": "Gesture detected on slider",
      "cursor_X": 648.8122,
      "cursor_y": 754.2547,
      "slider_position_X": 648.8122,
      "slider_value": 0
    },
    {
      "activity": "drawCalled",
      "state": "PinchDetected",
      "cursor_X": 649.8278,
      "cursor_y": 754.2946,
      "slider_position_X": 648.8122,
      "slider_value": 0
    },
    {
      "activity": "sliderMoved",
      "state": "PinchDetected",
      "message": "Gesture detected on slider",
      "cursor_X": 649.8278,
      "cursor_y": 754.2946,
      "slider_position_X": 649.8278,
      "slider_value": 0
    },
    {
      "activity": "drawCalled",
      "state": "PinchDetected",
      "cursor_X": 650.99786,
      "cursor_y": 754.3242,
      "slider_position_X": 649.8278,
      "slider_value": 0
    },
    {
      "activity": "sliderMoved",
      "state": "PinchDetected",
      "message": "Gesture detected on slider",
      "cursor_X": 650.99786,
      "cursor_y": 754.3242,
      "slider_position_X": 650.99786,
      "slider_value": 0
    },
    {
      "activity": "drawCalled",
      "state": "PinchDetected",
      "cursor_X": 652.3882,
      "cursor_y": 754.3425,
      "slider_position_X": 650.99786,
      "slider_value": 0
    },
    {
      "activity": "sliderMoved",
      "state": "PinchDetected",
      "message": "Gesture detected on slider",
      "cursor_X": 652.3882,
      "cursor_y": 754.3425,
      "slider_position_X": 652.3882,
      "slider_value": 0
    },
    {
      "activity": "drawCalled",
      "state": "PinchDetected",
      "cursor_X": 653.90393,
      "cursor_y": 754.33844,
      "slider_position_X": 652.3882,
      "slider_value": 0
    },
    {
      "activity": "sliderMoved",
      "state": "PinchDetected",
      "message": "Gesture detected on slider",
      "cursor_X": 653.90393,
      "cursor_y": 754.33844,
      "slider_position_X": 653.90393,
      "slider_value": 0
    },
    {
      "activity": "drawCalled",
      "state": "PinchDetected",
      "cursor_X": 655.5555,
      "cursor_y": 754.30505,
      "slider_position_X": 653.90393,
      "slider_value": 0
    },
    {
      "activity": "sliderMoved",
      "state": "PinchDetected",
      "message": "Gesture detected on slider",
      "cursor_X": 655.5555,
      "cursor_y": 754.30505,
      "slider_position_X": 655.5555,
      "slider_value": 0
    },
    {
      "activity": "drawCalled",
      "state": "PinchDetected",
      "cursor_X": 658.5387,
      "cursor_y": 754.1949,
      "slider_position_X": 655.5555,
      "slider_value": 0
    },
    {
      "activity": "sliderMoved",
      "state": "PinchDetected",
      "message": "Gesture detected on slider",
      "cursor_X": 658.5387,
      "cursor_y": 754.1949,
      "slider_position_X": 658.5387,
      "slider_value": 0
    },
    {
      "activity": "drawCalled",
      "state": "PinchDetected",
      "cursor_X": 661.11017,
      "cursor_y": 754.07227,
      "slider_position_X": 658.5387,
      "slider_value": 0
    },
    {
      "activity": "sliderMoved",
      "state": "PinchDetected",
      "message": "Gesture detected on slider",
      "cursor_X": 661.11017,
      "cursor_y": 754.07227,
      "slider_position_X": 661.11017,
      "slider_value": 0
    },
    {
      "activity": "drawCalled",
      "state": "PinchDetected",
      "cursor_X": 664.3598,
      "cursor_y": 753.8836,
      "slider_position_X": 661.11017,
      "slider_value": 0
    },
    {
      "activity": "sliderMoved",
      "state": "PinchDetected",
      "message": "Gesture detected on slider",
      "cursor_X": 664.3598,
      "cursor_y": 753.8836,
      "slider_position_X": 664.3598,
      "slider_value": 0
    },
    {
      "activity": "drawCalled",
      "state": "PinchDetected",
      "cursor_X": 668.5408,
      "cursor_y": 753.6033,
      "slider_position_X": 664.3598,
      "slider_value": 0
    },
    {
      "activity": "sliderMoved",
      "state": "PinchDetected",
      "message": "Gesture detected on slider",
      "cursor_X": 668.5408,
      "cursor_y": 753.6033,
      "slider_position_X": 668.5408,
      "slider_value": 0
    },
    {
      "activity": "drawCalled",
      "state": "PinchDetected",
      "cursor_X": 671.12177,
      "cursor_y": 753.42175,
      "slider_position_X": 668.5408,
      "slider_value": 0
    },
    {
      "activity": "sliderMoved",
      "state": "PinchDetected",
      "message": "Gesture detected on slider",
      "cursor_X": 671.12177,
      "cursor_y": 753.42175,
      "slider_position_X": 671.12177,
      "slider_value": 0
    },
    {
      "activity": "drawCalled",
      "state": "PinchDetected",
      "cursor_X": 671.12177,
      "cursor_y": 753.42175,
      "slider_position_X": 671.12177,
      "slider_value": 0
    },
    {
      "activity": "sliderMoved",
      "state": "PinchDetected",
      "message": "Gesture detected on slider",
      "cursor_X": 671.12177,
      "cursor_y": 753.42175,
      "slider_position_X": 671.12177,
      "slider_value": 0
    },
    {
      "activity": "drawCalled",
      "state": "PinchDetected",
      "cursor_X": 679.6448,
      "cursor_y": 752.70483,
      "slider_position_X": 671.12177,
      "slider_value": 0
    },
    {
      "activity": "sliderMoved",
      "state": "PinchDetected",
      "message": "Gesture detected on slider",
      "cursor_X": 679.6448,
      "cursor_y": 752.70483,
      "slider_position_X": 679.6448,
      "slider_value": 0
    },
    {
      "activity": "drawCalled",
      "state": "PinchDetected",
      "cursor_X": 708.4032,
      "cursor_y": 750.16345,
      "slider_position_X": 679.6448,
      "slider_value": 0
    },
    {
      "activity": "sliderMoved",
      "state": "PinchDetected",
      "message": "Gesture detected on slider",
      "cursor_X": 708.4032,
      "cursor_y": 750.16345,
      "slider_position_X": 708.4032,
      "slider_value": 0
    },
    {
      "activity": "drawCalled",
      "state": "PinchDetected",
      "cursor_X": 742.73224,
      "cursor_y": 747.0227,
      "slider_position_X": 708.4032,
      "slider_value": 0
    },
    {
      "activity": "sliderMoved",
      "state": "PinchDetected",
      "message": "Gesture detected on slider",
      "cursor_X": 742.73224,
      "cursor_y": 747.0227,
      "slider_position_X": 742.73224,
      "slider_value": 0
    },
    {
      "activity": "drawCalled",
      "state": "PinchDetected",
      "cursor_X": 780.6278,
      "cursor_y": 743.3996,
      "slider_position_X": 742.73224,
      "slider_value": 1
    },
    {
      "activity": "sliderMoved",
      "state": "PinchDetected",
      "message": "Gesture detected on slider",
      "cursor_X": 780.6278,
      "cursor_y": 743.3996,
      "slider_position_X": 780.6278,
      "slider_value": 1
    },
    {
      "activity": "drawCalled",
      "state": "PinchDetected",
      "cursor_X": 799.0825,
      "cursor_y": 741.5843,
      "slider_position_X": 780.6278,
      "slider_value": 1
    },
    {
      "activity": "sliderMoved",
      "state": "PinchDetected",
      "message": "Gesture detected on slider",
      "cursor_X": 799.0825,
      "cursor_y": 741.5843,
      "slider_position_X": 799.0825,
      "slider_value": 1
    },
    {
      "activity": "drawCalled",
      "state": "PinchDetected",
      "cursor_X": 854.053,
      "cursor_y": 736.2068,
      "slider_position_X": 799.0825,
      "slider_value": 1
    },
    {
      "activity": "sliderMoved",
      "state": "PinchDetected",
      "message": "Gesture detected on slider",
      "cursor_X": 854.053,
      "cursor_y": 736.2068,
      "slider_position_X": 854.053,
      "slider_value": 1
    },
    {
      "activity": "drawCalled",
      "state": "PinchDetected",
      "cursor_X": 887.83997,
      "cursor_y": 733.196,
      "slider_position_X": 854.053,
      "slider_value": 1
    },
    {
      "activity": "sliderMoved",
      "state": "PinchDetected",
      "message": "Gesture detected on slider",
      "cursor_X": 887.83997,
      "cursor_y": 733.196,
      "slider_position_X": 887.83997,
      "slider_value": 1
    },
    {
      "activity": "drawCalled",
      "state": "PinchDetected",
      "cursor_X": 908.4729,
      "cursor_y": 731.6033,
      "slider_position_X": 887.83997,
      "slider_value": 2
    },
    {
      "activity": "sliderMoved",
      "state": "PinchDetected",
      "message": "Gesture detected on slider",
      "cursor_X": 908.4729,
      "cursor_y": 731.6033,
      "slider_position_X": 908.4729,
      "slider_value": 2
    },
    {
      "activity": "drawCalled",
      "state": "PinchDetected",
      "cursor_X": 925.3708,
      "cursor_y": 730.5135,
      "slider_position_X": 908.4729,
      "slider_value": 2
    },
    {
      "activity": "sliderMoved",
      "state": "PinchDetected",
      "message": "Gesture detected on slider",
      "cursor_X": 925.3708,
      "cursor_y": 730.5135,
      "slider_position_X": 925.3708,
      "slider_value": 2
    },
    {
      "activity": "drawCalled",
      "state": "PinchDetected",
      "cursor_X": 939.8371,
      "cursor_y": 729.9505,
      "slider_position_X": 925.3708,
      "slider_value": 2
    },
    {
      "activity": "sliderMoved",
      "state": "PinchDetected",
      "message": "Gesture detected on slider",
      "cursor_X": 939.8371,
      "cursor_y": 729.9505,
      "slider_position_X": 939.8371,
      "slider_value": 2
    },
    {
      "activity": "drawCalled",
      "state": "PinchDetected",
      "cursor_X": 954.618,
      "cursor_y": 730.3819,
      "slider_position_X": 939.8371,
      "slider_value": 2
    },
    {
      "activity": "sliderMoved",
      "state": "PinchDetected",
      "message": "Gesture detected on slider",
      "cursor_X": 954.618,
      "cursor_y": 730.3819,
      "slider_position_X": 954.618,
      "slider_value": 2
    },
    {
      "activity": "drawCalled",
      "state": "PinchDetected",
      "cursor_X": 970.1617,
      "cursor_y": 731.2667,
      "slider_position_X": 954.618,
      "slider_value": 2
    },
    {
      "activity": "sliderMoved",
      "state": "PinchDetected",
      "message": "Gesture detected on slider",
      "cursor_X": 970.1617,
      "cursor_y": 731.2667,
      "slider_position_X": 970.1617,
      "slider_value": 2
    },
    {
      "activity": "drawCalled",
      "state": "PinchDetected",
      "cursor_X": 984.9298,
      "cursor_y": 732.11206,
      "slider_position_X": 970.1617,
      "slider_value": 2
    },
    {
      "activity": "sliderMoved",
      "state": "PinchDetected",
      "message": "Gesture detected on slider",
      "cursor_X": 984.9298,
      "cursor_y": 732.11206,
      "slider_position_X": 984.9298,
      "slider_value": 2
    },
    {
      "activity": "drawCalled",
      "state": "PinchDetected",
      "cursor_X": 999.20233,
      "cursor_y": 732.82733,
      "slider_position_X": 984.9298,
      "slider_value": 2
    },
    {
      "activity": "sliderMoved",
      "state": "PinchDetected",
      "message": "Gesture detected on slider",
      "cursor_X": 999.20233,
      "cursor_y": 732.82733,
      "slider_position_X": 999.20233,
      "slider_value": 2
    },
    {
      "activity": "drawCalled",
      "state": "PinchDetected",
      "cursor_X": 1011.1279,
      "cursor_y": 733.11206,
      "slider_position_X": 999.20233,
      "slider_value": 2
    },
    {
      "activity": "sliderMoved",
      "state": "PinchDetected",
      "message": "Gesture detected on slider",
      "cursor_X": 1011.1279,
      "cursor_y": 733.11206,
      "slider_position_X": 1011.1279,
      "slider_value": 2
    },
    {
      "activity": "drawCalled",
      "state": "PinchDetected",
      "cursor_X": 1020.757,
      "cursor_y": 732.8218,
      "slider_position_X": 1011.1279,
      "slider_value": 3
    },
    {
      "activity": "sliderMoved",
      "state": "PinchDetected",
      "message": "Gesture detected on slider",
      "cursor_X": 1020.757,
      "cursor_y": 732.8218,
      "slider_position_X": 1020.757,
      "slider_value": 3
    },
    {
      "activity": "drawCalled",
      "state": "PinchDetected",
      "cursor_X": 1030.1292,
      "cursor_y": 732.58405,
      "slider_position_X": 1020.757,
      "slider_value": 3
    },
    {
      "activity": "sliderMoved",
      "state": "PinchDetected",
      "message": "Gesture detected on slider",
      "cursor_X": 1030.1292,
      "cursor_y": 732.58405,
      "slider_position_X": 1030.1292,
      "slider_value": 3
    },
    {
      "activity": "drawCalled",
      "state": "PinchDetected",
      "cursor_X": 1039.2764,
      "cursor_y": 732.3328,
      "slider_position_X": 1030.1292,
      "slider_value": 3
    },
    {
      "activity": "sliderMoved",
      "state": "PinchDetected",
      "message": "Gesture detected on slider",
      "cursor_X": 1039.2764,
      "cursor_y": 732.3328,
      "slider_position_X": 1039.2764,
      "slider_value": 3
    },
    {
      "activity": "drawCalled",
      "state": "PinchDetected",
      "cursor_X": 1053.6011,
      "cursor_y": 732.19836,
      "slider_position_X": 1039.2764,
      "slider_value": 3
    },
    {
      "activity": "sliderMoved",
      "state": "PinchDetected",
      "message": "Gesture detected on slider",
      "cursor_X": 1053.6011,
      "cursor_y": 732.19836,
      "slider_position_X": 1053.6011,
      "slider_value": 3
    },
    {
      "activity": "drawCalled",
      "state": "PinchDetected",
      "cursor_X": 1061.5925,
      "cursor_y": 731.90625,
      "slider_position_X": 1053.6011,
      "slider_value": 3
    },
    {
      "activity": "sliderMoved",
      "state": "PinchDetected",
      "message": "Gesture detected on slider",
      "cursor_X": 1061.5925,
      "cursor_y": 731.90625,
      "slider_position_X": 1061.5925,
      "slider_value": 3
    },
    {
      "activity": "drawCalled",
      "state": "PinchDetected",
      "cursor_X": 1070.2615,
      "cursor_y": 731.7996,
      "slider_position_X": 1061.5925,
      "slider_value": 3
    },
    {
      "activity": "sliderMoved",
      "state": "PinchDetected",
      "message": "Gesture detected on slider",
      "cursor_X": 1070.2615,
      "cursor_y": 731.7996,
      "slider_position_X": 1070.2615,
      "slider_value": 3
    },
    {
      "activity": "drawCalled",
      "state": "PinchDetected",
      "cursor_X": 1078.3784,
      "cursor_y": 731.5477,
      "slider_position_X": 1070.2615,
      "slider_value": 3
    },
    {
      "activity": "sliderMoved",
      "state": "PinchDetected",
      "message": "Gesture detected on slider",
      "cursor_X": 1078.3784,
      "cursor_y": 731.5477,
      "slider_position_X": 1078.3784,
      "slider_value": 3
    },
    {
      "activity": "drawCalled",
      "state": "PinchDetected",
      "cursor_X": 1089.0989,
      "cursor_y": 731.0621,
      "slider_position_X": 1078.3784,
      "slider_value": 3
    },
    {
      "activity": "sliderMoved",
      "state": "PinchDetected",
      "message": "Gesture detected on slider",
      "cursor_X": 1089.0989,
      "cursor_y": 731.0621,
      "slider_position_X": 1089.0989,
      "slider_value": 3
    },
    {
      "activity": "drawCalled",
      "state": "PinchDetected",
      "cursor_X": 1096.2118,
      "cursor_y": 730.66864,
      "slider_position_X": 1089.0989,
      "slider_value": 3
    },
    {
      "activity": "sliderMoved",
      "state": "PinchDetected",
      "message": "Gesture detected on slider",
      "cursor_X": 1096.2118,
      "cursor_y": 730.66864,
      "slider_position_X": 1096.2118,
      "slider_value": 3
    },
    {
      "activity": "drawCalled",
      "state": "PinchDetected",
      "cursor_X": 1102.7256,
      "cursor_y": 729.83887,
      "slider_position_X": 1096.2118,
      "slider_value": 3
    },
    {
      "activity": "sliderMoved",
      "state": "PinchDetected",
      "message": "Gesture detected on slider",
      "cursor_X": 1102.7256,
      "cursor_y": 729.83887,
      "slider_position_X": 1102.7256,
      "slider_value": 3
    },
    {
      "activity": "drawCalled",
      "state": "PinchDetected",
      "cursor_X": 1109.6306,
      "cursor_y": 728.98315,
      "slider_position_X": 1102.7256,
      "slider_value": 3
    },
    {
      "activity": "sliderMoved",
      "state": "PinchDetected",
      "message": "Gesture detected on slider",
      "cursor_X": 1109.6306,
      "cursor_y": 728.98315,
      "slider_position_X": 1109.6306,
      "slider_value": 3
    },
    {
      "activity": "drawCalled",
      "state": "PinchDetected",
      "cursor_X": 1118.9926,
      "cursor_y": 727.4689,
      "slider_position_X": 1109.6306,
      "slider_value": 3
    },
    {
      "activity": "sliderMoved",
      "state": "PinchDetected",
      "message": "Gesture detected on slider",
      "cursor_X": 1118.9926,
      "cursor_y": 727.4689,
      "slider_position_X": 1118.9926,
      "slider_value": 3
    },
    {
      "activity": "drawCalled",
      "state": "PinchDetected",
      "cursor_X": 1124.9812,
      "cursor_y": 726.1779,
      "slider_position_X": 1118.9926,
      "slider_value": 3
    },
    {
      "activity": "sliderMoved",
      "state": "PinchDetected",
      "message": "Gesture detected on slider",
      "cursor_X": 1124.9812,
      "cursor_y": 726.1779,
      "slider_position_X": 1124.9812,
      "slider_value": 3
    },
    {
      "activity": "drawCalled",
      "state": "PinchDetected",
      "cursor_X": 1130.4727,
      "cursor_y": 725.1145,
      "slider_position_X": 1124.9812,
      "slider_value": 3
    },
    {
      "activity": "sliderMoved",
      "state": "PinchDetected",
      "message": "Gesture detected on slider",
      "cursor_X": 1130.4727,
      "cursor_y": 725.1145,
      "slider_position_X": 1130.4727,
      "slider_value": 3
    },
    {
      "activity": "drawCalled",
      "state": "PinchDetected",
      "cursor_X": 1135.5765,
      "cursor_y": 724.1659,
      "slider_position_X": 1130.4727,
      "slider_value": 3
    },
    {
      "activity": "sliderMoved",
      "state": "PinchDetected",
      "message": "Gesture detected on slider",
      "cursor_X": 1135.5765,
      "cursor_y": 724.1659,
      "slider_position_X": 1135.5765,
      "slider_value": 3
    },
    {
      "activity": "drawCalled",
      "state": "PinchDetected",
      "cursor_X": 1140.8169,
      "cursor_y": 723.461,
      "slider_position_X": 1135.5765,
      "slider_value": 3
    },
    {
      "activity": "sliderMoved",
      "state": "PinchDetected",
      "message": "Gesture detected on slider",
      "cursor_X": 1140.8169,
      "cursor_y": 723.461,
      "slider_position_X": 1140.8169,
      "slider_value": 3
    },
    {
      "activity": "drawCalled",
      "state": "PinchDetected",
      "cursor_X": 1147.3779,
      "cursor_y": 723.13745,
      "slider_position_X": 1140.8169,
      "slider_value": 3
    },
    {
      "activity": "sliderMoved",
      "state": "PinchDetected",
      "message": "Gesture detected on slider",
      "cursor_X": 1147.3779,
      "cursor_y": 723.13745,
      "slider_position_X": 1147.3779,
      "slider_value": 3
    },
    {
      "activity": "drawCalled",
      "state": "PinchDetected",
      "cursor_X": 1153.8466,
      "cursor_y": 722.93176,
      "slider_position_X": 1147.3779,
      "slider_value": 4
    },
    {
      "activity": "sliderMoved",
      "state": "PinchDetected",
      "message": "Gesture detected on slider",
      "cursor_X": 1153.8466,
      "cursor_y": 722.93176,
      "slider_position_X": 1153.8466,
      "slider_value": 4
    },
    {
      "activity": "drawCalled",
      "state": "PinchDetected",
      "cursor_X": 1160.0977,
      "cursor_y": 722.74225,
      "slider_position_X": 1153.8466,
      "slider_value": 4
    },
    {
      "activity": "sliderMoved",
      "state": "PinchDetected",
      "message": "Gesture detected on slider",
      "cursor_X": 1160.0977,
      "cursor_y": 722.74225,
      "slider_position_X": 1160.0977,
      "slider_value": 4
    },
    {
      "activity": "drawCalled",
      "state": "PinchDetected",
      "cursor_X": 1165.6434,
      "cursor_y": 722.50995,
      "slider_position_X": 1160.0977,
      "slider_value": 4
    },
    {
      "activity": "sliderMoved",
      "state": "PinchDetected",
      "message": "Gesture detected on slider",
      "cursor_X": 1165.6434,
      "cursor_y": 722.50995,
      "slider_position_X": 1165.6434,
      "slider_value": 4
    },
    {
      "activity": "drawCalled",
      "state": "PinchDetected",
      "cursor_X": 1173.5826,
      "cursor_y": 722.2624,
      "slider_position_X": 1165.6434,
      "slider_value": 4
    },
    {
      "activity": "sliderMoved",
      "state": "PinchDetected",
      "message": "Gesture detected on slider",
      "cursor_X": 1173.5826,
      "cursor_y": 722.2624,
      "slider_position_X": 1173.5826,
      "slider_value": 4
    },
    {
      "activity": "drawCalled",
      "state": "PinchDetected",
      "cursor_X": 1178.5826,
      "cursor_y": 722.13086,
      "slider_position_X": 1173.5826,
      "slider_value": 4
    },
    {
      "activity": "sliderMoved",
      "state": "PinchDetected",
      "message": "Gesture detected on slider",
      "cursor_X": 1178.5826,
      "cursor_y": 722.13086,
      "slider_position_X": 1178.5826,
      "slider_value": 4
    },
    {
      "activity": "drawCalled",
      "state": "PinchDetected",
      "cursor_X": 1183.2423,
      "cursor_y": 721.92834,
      "slider_position_X": 1178.5826,
      "slider_value": 4
    },
    {
      "activity": "sliderMoved",
      "state": "PinchDetected",
      "message": "Gesture detected on slider",
      "cursor_X": 1183.2423,
      "cursor_y": 721.92834,
      "slider_position_X": 1183.2423,
      "slider_value": 4
    },
    {
      "activity": "drawCalled",
      "state": "PinchDetected",
      "cursor_X": 1187.7545,
      "cursor_y": 721.8449,
      "slider_position_X": 1183.2423,
      "slider_value": 4
    },
    {
      "activity": "sliderMoved",
      "state": "PinchDetected",
      "message": "Gesture detected on slider",
      "cursor_X": 1187.7545,
      "cursor_y": 721.8449,
      "slider_position_X": 1187.7545,
      "slider_value": 4
    },
    {
      "activity": "drawCalled",
      "state": "PinchDetected",
      "cursor_X": 1191.8783,
      "cursor_y": 721.9066,
      "slider_position_X": 1187.7545,
      "slider_value": 4
    },
    {
      "activity": "sliderMoved",
      "state": "PinchDetected",
      "message": "Gesture detected on slider",
      "cursor_X": 1191.8783,
      "cursor_y": 721.9066,
      "slider_position_X": 1191.8783,
      "slider_value": 4
    },
    {
      "activity": "drawCalled",
      "state": "PinchDetected",
      "cursor_X": 1195.6329,
      "cursor_y": 721.9468,
      "slider_position_X": 1191.8783,
      "slider_value": 4
    },
    {
      "activity": "sliderMoved",
      "state": "PinchDetected",
      "message": "Gesture detected on slider",
      "cursor_X": 1195.6329,
      "cursor_y": 721.9468,
      "slider_position_X": 1195.6329,
      "slider_value": 4
    },
    {
      "activity": "drawCalled",
      "state": "PinchDetected",
      "cursor_X": 1198.9489,
      "cursor_y": 721.9071,
      "slider_position_X": 1195.6329,
      "slider_value": 4
    },
    {
      "activity": "sliderMoved",
      "state": "PinchDetected",
      "message": "Gesture detected on slider",
      "cursor_X": 1198.9489,
      "cursor_y": 721.9071,
      "slider_position_X": 1198.9489,
      "slider_value": 4
    },
    {
      "activity": "drawCalled",
      "state": "PinchDetected",
      "cursor_X": 1201.9023,
      "cursor_y": 721.9197,
      "slider_position_X": 1198.9489,
      "slider_value": 4
    },
    {
      "activity": "sliderMoved",
      "state": "PinchDetected",
      "message": "Gesture detected on slider",
      "cursor_X": 1201.9023,
      "cursor_y": 721.9197,
      "slider_position_X": 1201.9023,
      "slider_value": 4
    },
    {
      "activity": "drawCalled",
      "state": "PinchDetected",
      "cursor_X": 1205.6044,
      "cursor_y": 722.032,
      "slider_position_X": 1201.9023,
      "slider_value": 4
    },
    {
      "activity": "sliderMoved",
      "state": "PinchDetected",
      "message": "Gesture detected on slider",
      "cursor_X": 1205.6044,
      "cursor_y": 722.032,
      "slider_position_X": 1205.6044,
      "slider_value": 4
    },
    {
      "activity": "drawCalled",
      "state": "PinchDetected",
      "cursor_X": 1207.7346,
      "cursor_y": 722.06866,
      "slider_position_X": 1205.6044,
      "slider_value": 4
    },
    {
      "activity": "sliderMoved",
      "state": "PinchDetected",
      "message": "Gesture detected on slider",
      "cursor_X": 1207.7346,
      "cursor_y": 722.06866,
      "slider_position_X": 1207.7346,
      "slider_value": 4
    },
    {
      "activity": "drawCalled",
      "state": "PinchDetected",
      "cursor_X": 1209.656,
      "cursor_y": 722.0798,
      "slider_position_X": 1207.7346,
      "slider_value": 4
    },
    {
      "activity": "sliderMoved",
      "state": "PinchDetected",
      "message": "Gesture detected on slider",
      "cursor_X": 1209.656,
      "cursor_y": 722.0798,
      "slider_position_X": 1209.656,
      "slider_value": 4
    },
    {
      "activity": "drawCalled",
      "state": "PinchDetected",
      "cursor_X": 1212.0198,
      "cursor_y": 722.0628,
      "slider_position_X": 1209.656,
      "slider_value": 4
    },
    {
      "activity": "sliderMoved",
      "state": "PinchDetected",
      "message": "Gesture detected on slider",
      "cursor_X": 1212.0198,
      "cursor_y": 722.0628,
      "slider_position_X": 1212.0198,
      "slider_value": 4
    },
    {
      "activity": "drawCalled",
      "state": "PinchDetected",
      "cursor_X": 1213.29,
      "cursor_y": 722.0249,
      "slider_position_X": 1212.0198,
      "slider_value": 4
    },
    {
      "activity": "sliderMoved",
      "state": "PinchDetected",
      "message": "Gesture detected on slider",
      "cursor_X": 1213.29,
      "cursor_y": 722.0249,
      "slider_position_X": 1213.29,
      "slider_value": 4
    },
    {
      "activity": "drawCalled",
      "state": "PinchDetected",
      "cursor_X": 1214.7273,
      "cursor_y": 721.8653,
      "slider_position_X": 1213.29,
      "slider_value": 4
    },
    {
      "activity": "sliderMoved",
      "state": "PinchDetected",
      "message": "Gesture detected on slider",
      "cursor_X": 1214.7273,
      "cursor_y": 721.8653,
      "slider_position_X": 1214.7273,
      "slider_value": 4
    },
    {
      "activity": "drawCalled",
      "state": "PinchDetected",
      "cursor_X": 1215.4323,
      "cursor_y": 721.7176,
      "slider_position_X": 1214.7273,
      "slider_value": 4
    },
    {
      "activity": "sliderMoved",
      "state": "PinchDetected",
      "message": "Gesture detected on slider",
      "cursor_X": 1215.4323,
      "cursor_y": 721.7176,
      "slider_position_X": 1215.4323,
      "slider_value": 4
    },
    {
      "activity": "drawCalled",
      "state": "PinchDetected",
      "cursor_X": 1216.0082,
      "cursor_y": 721.5426,
      "slider_position_X": 1215.4323,
      "slider_value": 4
    },
    {
      "activity": "sliderMoved",
      "state": "PinchDetected",
      "message": "Gesture detected on slider",
      "cursor_X": 1216.0082,
      "cursor_y": 721.5426,
      "slider_position_X": 1216.0082,
      "slider_value": 4
    },
    {
      "activity": "drawCalled",
      "state": "PinchDetected",
      "cursor_X": 1216.4233,
      "cursor_y": 721.3332,
      "slider_position_X": 1216.0082,
      "slider_value": 4
    },
    {
      "activity": "sliderMoved",
      "state": "PinchDetected",
      "message": "Gesture detected on slider",
      "cursor_X": 1216.4233,
      "cursor_y": 721.3332,
      "slider_position_X": 1216.4233,
      "slider_value": 4
    },
    {
      "activity": "drawCalled",
      "state": "PinchDetected",
      "cursor_X": 1216.6401,
      "cursor_y": 721.09045,
      "slider_position_X": 1216.4233,
      "slider_value": 4
    },
    {
      "activity": "sliderMoved",
      "state": "PinchDetected",
      "message": "Gesture detected on slider",
      "cursor_X": 1216.6401,
      "cursor_y": 721.09045,
      "slider_position_X": 1216.6401,
      "slider_value": 4
    },
    {
      "activity": "drawCalled",
      "state": "PinchDetected",
      "cursor_X": 1216.7191,
      "cursor_y": 720.84155,
      "slider_position_X": 1216.6401,
      "slider_value": 4
    },
    {
      "activity": "sliderMoved",
      "state": "PinchDetected",
      "message": "Gesture detected on slider",
      "cursor_X": 1216.7191,
      "cursor_y": 720.84155,
      "slider_position_X": 1216.7191,
      "slider_value": 4
    },
    {
      "activity": "drawCalled",
      "state": "PinchDetected",
      "cursor_X": 1216.7034,
      "cursor_y": 720.5976,
      "slider_position_X": 1216.7191,
      "slider_value": 4
    },
    {
      "activity": "sliderMoved",
      "state": "PinchDetected",
      "message": "Gesture detected on slider",
      "cursor_X": 1216.7034,
      "cursor_y": 720.5976,
      "slider_position_X": 1216.7034,
      "slider_value": 4
    },
    {
      "activity": "drawCalled",
      "state": "PinchDetected",
      "cursor_X": 1216.5479,
      "cursor_y": 720.2522,
      "slider_position_X": 1216.7034,
      "slider_value": 4
    },
    {
      "activity": "sliderMoved",
      "state": "PinchDetected",
      "message": "Gesture detected on slider",
      "cursor_X": 1216.5479,
      "cursor_y": 720.2522,
      "slider_position_X": 1216.5479,
      "slider_value": 4
    },
    {
      "activity": "BlockCompleted",
      "state": "PinchDetected",
      "message": "Block 12 complete",
      "cursor_X": 1216.5479,
      "cursor_y": 720.2522,
      "slider_position_X": 1216.5479,
      "slider_value": 4
    }
  ]
}