{
  "PID": -1,
  "gesture": "pinchAny",
  "task": "digitSelector",
  "target": 8,
  "block": 0,
  "startTime": 32490,
  "endTime": 35018,
  "frames": [
    {
      "activity": "drawCalled",
      "state": "NoHands",
      "cursor_X": 1300.4481,
      "cursor_y": 839.0234,
      "slider_position_X": 600.0,
      "slider_value": 0
    },
    {
      "activity": "StateTransition",
      "state": "NoHands",
      "message": "Transitioning from states NoHands to NoPinchDetected",
      "cursor_X": 1300.4481,
      "cursor_y": 839.0234,
      "slider_position_X": 600.0,
      "slider_value": 0
    },
    {
      "activity": "drawCalled",
      "state": "NoPinchDetected",
      "cursor_X": 1300.4503,
      "cursor_y": 838.9683,
      "slider_position_X": 600.0,
      "slider_value": 0
    },
    {
      "activity": "drawCalled",
      "state": "NoPinchDetected",
      "cursor_X": 1300.4535,
      "cursor_y": 838.94006,
      "slider_position_X": 600.0,
      "slider_value": 0
    },
    {
      "activity": "drawCalled",
      "state": "NoPinchDetected",
      "cursor_X": 1300.4557,
      "cursor_y": 838.9263,
      "slider_position_X": 600.0,
      "slider_value": 0
    },
    {
      "activity": "drawCalled",
      "state": "NoPinchDetected",
      "cursor_X": 1300.4564,
      "cursor_y": 838.9224,
      "slider_position_X": 600.0,
      "slider_value": 0
    },
    {
      "activity": "drawCalled",
      "state": "NoPinchDetected",
      "cursor_X": 1300.4572,
      "cursor_y": 838.91833,
      "slider_position_X": 600.0,
      "slider_value": 0
    },
    {
      "activity": "drawCalled",
      "state": "NoPinchDetected",
      "cursor_X": 1300.4573,
      "cursor_y": 838.91736,
      "slider_position_X": 600.0,
      "slider_value": 0
    },
    {
      "activity": "drawCalled",
      "state": "NoPinchDetected",
      "cursor_X": 1300.4574,
      "cursor_y": 838.9161,
      "slider_position_X": 600.0,
      "slider_value": 0
    },
    {
      "activity": "drawCalled",
      "state": "NoPinchDetected",
      "cursor_X": 1300.457,
      "cursor_y": 838.9096,
      "slider_position_X": 600.0,
      "slider_value": 0
    },
    {
      "activity": "drawCalled",
      "state": "NoPinchDetected",
      "cursor_X": 1300.4325,
      "cursor_y": 838.8706,
      "slider_position_X": 600.0,
      "slider_value": 0
    },
    {
      "activity": "drawCalled",
      "state": "NoPinchDetected",
      "cursor_X": 1300.2882,
      "cursor_y": 838.7653,
      "slider_position_X": 600.0,
      "slider_value": 0
    },
    {
      "activity": "drawCalled",
      "state": "NoPinchDetected",
      "cursor_X": 1298.3645,
      "cursor_y": 838.2794,
      "slider_position_X": 600.0,
      "slider_value": 0
    },
    {
      "activity": "drawCalled",
      "state": "NoPinchDetected",
      "cursor_X": 1296.1097,
      "cursor_y": 837.97284,
      "slider_position_X": 600.0,
      "slider_value": 0
    },
    {
      "activity": "drawCalled",
      "state": "NoPinchDetected",
      "cursor_X": 1274.2417,
      "cursor_y": 836.7214,
      "slider_position_X": 600.0,
      "slider_value": 0
    },
    {
      "activity": "drawCalled",
      "state": "NoPinchDetected",
      "cursor_X": 1236.1666,
      "cursor_y": 835.6755,
      "slider_position_X": 600.0,
      "slider_value": 0
    },
    {
      "activity": "drawCalled",
      "state": "NoPinchDetected",
      "cursor_X": 1177.269,
      "cursor_y": 834.61487,
      "slider_position_X": 600.0,
      "slider_value": 0
    },
    {
      "activity": "drawCalled",
      "state": "NoPinchDetected",
      "cursor_X": 1113.3735,
      "cursor_y": 834.3693,
      "slider_position_X": 600.0,
      "slider_value": 0
    },
    {
      "activity": "drawCalled",
      "state": "NoPinchDetected",
      "cursor_X": 1082.8312,
      "cursor_y": 835.1306,
      "slider_position_X": 600.0,
      "slider_value": 0
    },
    {
      "activity": "drawCalled",
      "state": "NoPinchDetected",
      "cursor_X": 1029.0565,
      "cursor_y": 836.5274,
      "slider_position_X": 600.0,
      "slider_value": 0
    },
    {
      "activity": "drawCalled",
      "state": "NoPinchDetected",
      "cursor_X": 983.6393,
      "cursor_y": 838.4823,
      "slider_position_X": 600.0,
      "slider_value": 0
    },
    {
      "activity": "drawCalled",
      "state": "NoPinchDetected",
      "cursor_X": 933.5748,
      "cursor_y": 836.0859,
      "slider_position_X": 600.0,
      "slider_value": 0
    },
    {
      "activity": "drawCalled",
      "state": "NoPinchDetected",
      "cursor_X": 884.9347,
      "cursor_y": 831.087,
      "slider_position_X": 600.0,
      "slider_value": 0
    },
    {
      "activity": "drawCalled",
      "state": "NoPinchDetected",
      "cursor_X": 860.5503,
      "cursor_y": 827.7206,
      "slider_position_X": 600.0,
      "slider_value": 0
    },
    {
      "activity": "drawCalled",
      "state": "NoPinchDetected",
      "cursor_X": 825.58325,
      "cursor_y": 825.64014,
      "slider_position_X": 600.0,
      "slider_value": 0
    },
    {
      "activity": "drawCalled",
      "state": "NoPinchDetected",
      "cursor_X": 797.39294,
      "cursor_y": 824.2421,
      "slider_position_X": 600.0,
      "slider_value": 0
    },
    {
      "activity": "drawCalled",
      "state": "NoPinchDetected",
      "cursor_X": 785.95123,
      "cursor_y": 824.45215,
      "slider_position_X": 600.0,
      "slider_value": 0
    },
    {
      "activity": "drawCalled",
      "state": "NoPinchDetected",
      "cursor_X": 763.8363,
      "cursor_y": 823.82684,
      "slider_position_X": 600.0,
      "slider_value": 0
    },
    {
      "activity": "drawCalled",
      "state": "NoPinchDetected",
      "cursor_X": 745.9654,
      "cursor_y": 823.3343,
      "slider_position_X": 600.0,
      "slider_value": 0
    },
    {
      "activity": "drawCalled",
      "state": "NoPinchDetected",
      "cursor_X": 732.0583,
      "cursor_y": 823.2404,
      "slider_position_X": 600.0,
      "slider_value": 0
    },
    {
      "activity": "drawCalled",
      "state": "NoPinchDetected",
      "cursor_X": 726.4199,
      "cursor_y": 823.2292,
      "slider_position_X": 600.0,
      "slider_value": 0
    },
    {
      "activity": "drawCalled",
      "state": "NoPinchDetected",
      "cursor_X": 716.6564,
      "cursor_y": 823.3196,
      "slider_position_X": 600.0,
      "slider_value": 0
    },
    {
      "activity": "drawCalled",
      "state": "NoPinchDetected",
      "cursor_X": 709.93036,
      "cursor_y": 823.36005,
      "slider_position_X": 600.0,
      "slider_value": 0
    },
    {
      "activity": "drawCalled",
      "state": "NoPinchDetected",
      "cursor_X": 707.6857,
      "cursor_y": 823.3879,
      "slider_position_X": 600.0,
      "slider_value": 0
    },
    {
      "activity": "drawCalled",
      "state": "NoPinchDetected",
      "cursor_X": 705.0963,
      "cursor_y": 823.4237,
      "slider_position_X": 600.0,
      "slider_value": 0
    },
    {
      "activity": "drawCalled",
      "state": "NoPinchDetected",
      "cursor_X": 705.6501,
      "cursor_y": 824.0123,
      "slider_position_X": 600.0,
      "slider_value": 0
    },
    {
      "activity": "drawCalled",
      "state": "NoPinchDetected",
      "cursor_X": 706.3027,
      "cursor_y": 824.37506,
      "slider_position_X": 600.0,
      "slider_value": 0
    },
    {
      "activity": "drawCalled",
      "state": "NoPinchDetected",
      "cursor_X": 708.07404,
      "cursor_y": 825.0955,
      "slider_position_X": 600.0,
      "slider_value": 0
    },
    {
      "activity": "gestureDetected",
      "state": "NoPinchDetected",
      "message": "Gesture detected",
      "cursor_X": 708.07404,
      "cursor_y": 825.0955,
      "slider_position_X": 600.0,
      "slider_value": 0
    },
    {
      "activity": "StateTransition",
      "state": "NoPinchDetected",
      "message": "Transitioning from states NoPinchDetected to PinchDetected",
      "cursor_X": 708.07404,
      "cursor_y": 825.0955,
      "slider_position_X": 600.0,
      "slider_value": 0
    },
    {
      "activity": "drawCalled",
      "state": "PinchDetected",
      "cursor_X": 711.16235,
      "cursor_y": 826.1502,
      "slider_position_X": 600.0,
      "slider_value": 0
    },
    {
      "activity": "drawCalled",
      "state": "PinchDetected",
      "cursor_X": 714.7747,
      "cursor_y": 826.98615,
      "slider_position_X": 603.0883,
      "slider_value": 0
    },
    {
      "activity": "drawCalled",
      "state": "PinchDetected",
      "cursor_X": 717.9932,
      "cursor_y": 827.5294,
      "slider_position_X": 606.7007,
      "slider_value": 0
    },
    {
      "activity": "drawCalled",
      "state": "PinchDetected",
      "cursor_X": 719.20776,
      "cursor_y": 827.66486,
      "slider_position_X": 609.9192,
      "slider_value": 0
    },
    {
      "activity": "drawCalled",
      "state": "PinchDetected",
      "cursor_X": 720.4266,
      "cursor_y": 827.79736,
      "slider_position_X": 611.1337,
      "slider_value": 0
    },
    {
      "activity": "drawCalled",
      "state": "PinchDetected",
      "cursor_X": 720.4266,
      "cursor_y": 827.79736,
      "slider_position_X": 612.35254,
      "slider_value": 0
    },
    {
      "activity": "drawCalled",
      "state": "PinchDetected",
      "cursor_X": 732.96716,
      "cursor_y": 828.96625,
      "slider_position_X": 612.35254,
      "slider_value": 0
    },
    {
      "activity": "drawCalled",
      "state": "PinchDetected",
      "cursor_X": 741.5806,
      "cursor_y": 829.4324,
      "slider_position_X": 624.8931,
      "slider_value": 0
    },
    {
      "activity": "drawCalled",
      "state": "PinchDetected",
      "cursor_X": 746.55286,
      "cursor_y": 829.5521,
      "slider_position_X": 633.5066,
      "slider_value": 0
    },
    {
      "activity": "drawCalled",
      "state": "PinchDetected",
      "cursor_X": 758.0083,
      "cursor_y": 829.8456,
      "slider_position_X": 638.4788,
      "slider_value": 0
    },
    {
      "activity": "drawCalled",
      "state": "PinchDetected",
      "cursor_X": 773.1766,
      "cursor_y": 830.27594,
      "slider_position_X": 649.93427,
      "slider_value": 0
    },
    {
      "activity": "drawCalled",
      "state": "PinchDetected",
      "cursor_X": 791.9273,
      "cursor_y": 830.69293,
      "slider_position_X": 665.10254,
      "slider_value": 0
    },
    {
      "activity": "drawCalled",
      "state": "PinchDetected",
      "cursor_X": 814.36523,
      "cursor_y": 830.991,
      "slider_position_X": 683.8533,
      "slider_value": 0
    },
    {
      "activity": "drawCalled",
      "state": "PinchDetected",
      "cursor_X": 855.3751,
      "cursor_y": 831.751,
      "slider_position_X": 706.2912,
      "slider_value": 0
    },
    {
      "activity": "drawCalled",
      "state": "PinchDetected",
      "cursor_X": 916.82214,
      "cursor_y": 832.40424,
      "slider_position_X": 747.3011,
      "slider_value": 1
    },
    {
      "activity": "drawCalled",
      "state": "PinchDetected",
      "cursor_X": 972.23376,
      "cursor_y": 833.86743,
      "slider_position_X": 808.7481,
      "slider_value": 1
    },
    {
      "activity": "drawCalled",
      "state": "PinchDetected",
      "cursor_X": 1023.1202,
      "cursor_y": 834.72314,
      "slider_position_X": 864.1597,
      "slider_value": 1
    },
    {
      "activity": "drawCalled",
      "state": "PinchDetected",
      "cursor_X": 1055.5631,
      "cursor_y": 834.866,
      "slider_position_X": 915.04614,
      "slider_value": 2
    },
    {
      "activity": "drawCalled",
      "state": "PinchDetected",
      "cursor_X": 1083.8232,
      "cursor_y": 834.0358,
      "slider_position_X": 947.4891,
      "slider_value": 2
    },
    {
      "activity": "drawCalled",
      "state": "PinchDetected",
      "cursor_X": 1108.8735,
      "cursor_y": 832.45294,
      "slider_position_X": 975.7492,
      "slider_value": 2
    },
    {
      "activity": "drawCalled",
      "state": "PinchDetected",
      "cursor_X": 1134.2852,
      "cursor_y": 830.71954,
      "slider_position_X": 1000.7995,
      "slider_value": 2
    },
    {
      "activity": "drawCalled",
      "state": "PinchDetected",
      "cursor_X": 1188.0983,
      "cursor_y": 833.31433,
      "slider_position_X": 1026.2112,
      "slider_value": 3
    },
    {
      "activity": "drawCalled",
      "state": "PinchDetected",
      "cursor_X": 1235.5676,
      "cursor_y": 831.33453,
      "slider_position_X": 1080.0242,
      "slider_value": 3
    },
    {
      "activity": "drawCalled",
      "state": "PinchDetected",
      "cursor_X": 1301.7244,
      "cursor_y": 830.1783,
      "slider_position_X": 1127.4937,
      "slider_value": 3
    },
    {
      "activity": "drawCalled",
      "state": "PinchDetected",
      "cursor_X": 1318.6948,
      "cursor_y": 829.3638,
      "slider_position_X": 1193.6504,
      "slider_value": 4
    },
    {
      "activity": "drawCalled",
      "state": "PinchDetected",
      "cursor_X": 1353.1323,
      "cursor_y": 829.545,
      "slider_position_X": 1210.6208,
      "slider_value": 4
    },
    {
      "activity": "drawCalled",
      "state": "PinchDetected",
      "cursor_X": 1388.6373,
      "cursor_y": 831.0926,
      "slider_position_X": 1245.0583,
      "slider_value": 4
    },
    {
      "activity": "drawCalled",
      "state": "PinchDetected",
      "cursor_X": 1424.5574,
      "cursor_y": 830.13135,
      "slider_position_X": 1280.5632,
      "slider_value": 5
    },
    {
      "activity": "drawCalled",
      "state": "PinchDetected",
      "cursor_X": 1499.0165,
      "cursor_y": 825.67163,
      "slider_position_X": 1316.4834,
      "slider_value": 5
    },
    {
      "activity": "drawCalled",
      "state": "PinchDetected",
      "cursor_X": 1554.1521,
      "cursor_y": 821.7699,
      "slider_position_X": 1390.9424,
      "slider_value": 5
    },
    {
      "activity": "drawCalled",
      "state": "PinchDetected",
      "cursor_X": 1607.9286,
      "cursor_y": 817.98444,
      "slider_position_X": 1446.0781,
      "slider_value": 6
    },
    {
      "activity": "drawCalled",
      "state": "PinchDetected",
      "cursor_X": 1654.757,
      "cursor_y": 817.3309,
      "slider_position_X": 1499.8545,
      "slider_value": 6
    },
    {
      "activity": "drawCalled",
      "state": "PinchDetected",
      "cursor_X": 1668.6157,
      "cursor_y": 815.64386,
      "slider_position_X": 1546.6829,
      "slider_value": 6
    },
    {
      "activity": "drawCalled",
      "state": "PinchDetected",
      "cursor_X": 1695.8973,
      "cursor_y": 813.13306,
      "slider_position_X": 1560.5417,
      "slider_value": 7
    },
    {
      "activity": "drawCalled",
      "state": "PinchDetected",
      "cursor_X": 1716.9088,
      "cursor_y": 812.0924,
      "slider_position_X": 1587.8232,
      "slider_value": 7
    },
    {
      "activity": "drawCalled",
      "state": "PinchDetected",
      "cursor_X": 1735.5374,
      "cursor_y": 810.434,
      "slider_position_X": 1608.8347,
      "slider_value": 7
    },
    {
      "activity": "drawCalled",
      "state": "PinchDetected",
      "cursor_X": 1752.2415,
      "cursor_y": 807.342,
      "slider_position_X": 1627.4634,
      "slider_value": 7
    },
    {
      "activity": "drawCalled",
      "state": "PinchDetected",
      "cursor_X": 1779.7756,
      "cursor_y": 801.5259,
      "slider_position_X": 1644.1675,
      "slider_value": 7
    },
    {
      "activity": "drawCalled",
      "state": "PinchDetected",
      "cursor_X": 1803.2039,
      "cursor_y": 799.96466,
      "slider_position_X": 1671.7017,
      "slider_value": 7
    },
    {
      "activity": "drawCalled",
      "state": "PinchDetected",
      "cursor_X": 1817.5054,
      "cursor_y": 801.1135,
      "slider_position_X": 1695.1299,
      "slider_value": 8
    },
    {
      "activity": "drawCalled",
      "state": "PinchDetected",
      "cursor_X": 1824.1707,
      "cursor_y": 801.6401,
      "slider_position_X": 1709.4314,
      "slider_value": 8
    },
    {
      "activity": "drawCalled",
      "state": "PinchDetected",
      "cursor_X": 1827.1372,
      "cursor_y": 802.01965,
      "slider_position_X": 1716.0967,
      "slider_value": 8
    },
    {
      "activity": "drawCalled",
      "state": "PinchDetected",
      "cursor_X": 1831.6539,
      "cursor_y": 802.58435,
      "slider_position_X": 1719.0632,
      "slider_value": 8
    },
    {
      "activity": "drawCalled",
      "state": "PinchDetected",
      "cursor_X": 1837.5823,
      "cursor_y": 803.0039,
      "slider_position_X": 1723.5798,
      "slider_value": 8
    },
    {
      "activity": "drawCalled",
      "state": "PinchDetected",
      "cursor_X": 1842.0669,
      "cursor_y": 803.3815,
      "slider_position_X": 1729.5083,
      "slider_value": 8
    },
    {
      "activity": "drawCalled",
      "state": "PinchDetected",
      "cursor_X": 1847.6931,
      "cursor_y": 803.7283,
      "slider_position_X": 1733.9929,
      "slider_value": 8
    },
    {
      "activity": "drawCalled",
      "state": "PinchDetected",
      "cursor_X": 1852.3064,
      "cursor_y": 804.0198,
      "slider_position_X": 1739.6191,
      "slider_value": 8
    },
    {
      "activity": "drawCalled",
      "state": "PinchDetected",
      "cursor_X": 1854.9929,
      "cursor_y": 804.3647,
      "slider_position_X": 1744.2324,
      "slider_value": 8
    },
    {
      "activity": "drawCalled",
      "state": "PinchDetected",
      "cursor_X": 1857.267,
      "cursor_y": 804.73047,
      "slider_position_X": 1746.919,
      "slider_value": 8
    },
    {
      "activity": "drawCalled",
      "state": "PinchDetected",
      "cursor_X": 1859.2642,
      "cursor_y": 805.14417,
      "slider_position_X": 1749.1929,
      "slider_value": 8
    },
    {
      "activity": "drawCalled",
      "state": "PinchDetected",
      "cursor_X": 1860.1667,
      "cursor_y": 805.3488,
      "slider_position_X": 1751.1902,
      "slider_value": 8
    },
    {
      "activity": "drawCalled",
      "state": "PinchDetected",
      "cursor_X": 1861.7681,
      "cursor_y": 805.72736,
      "slider_position_X": 1752.0928,
      "slider_value": 8
    },
    {
      "activity": "drawCalled",
      "state": "PinchDetected",
      "cursor_X": 1864.3226,
      "cursor_y": 806.2422,
      "slider_position_X": 1753.6941,
      "slider_value": 8
    },
    {
      "activity": "drawCalled",
      "state": "PinchDetected",
      "cursor_X": 1865.5931,
      "cursor_y": 806.5346,
      "slider_position_X": 1756.2485,
      "slider_value": 8
    },
    {
      "activity": "drawCalled",
      "state": "PinchDetected",
      "cursor_X": 1866.5441,
      "cursor_y": 806.7437,
      "slider_position_X": 1757.519,
      "slider_value": 8
    },
    {
      "activity": "drawCalled",
      "state": "PinchDetected",
      "cursor_X": 1866.9491,
      "cursor_y": 806.82965,
      "slider_position_X": 1758.47,
      "slider_value": 8
    },
    {
      "activity": "drawCalled",
      "state": "PinchDetected",
      "cursor_X": 1866.9491,
      "cursor_y": 806.82965,
      "slider_position_X": 1758.875,
      "slider_value": 8
    },
    {
      "activity": "drawCalled",
      "state": "PinchDetected",
      "cursor_X": 1867.1802,
      "cursor_y": 806.83344,
      "slider_position_X": 1758.875,
      "slider_value": 8
    },
    {
      "activity": "drawCalled",
      "state": "PinchDetected",
      "cursor_X": 1867.2941,
      "cursor_y": 806.74756,
      "slider_position_X": 1759.1062,
      "slider_value": 8
    },
    {
      "activity": "drawCalled",
      "state": "PinchDetected",
      "cursor_X": 1867.4636,
      "cursor_y": 806.52496,
      "slider_position_X": 1759.22,
      "slider_value": 8
    },
    {
      "activity": "drawCalled",
      "state": "PinchDetected",
      "cursor_X": 1867.4285,
      "cursor_y": 806.47766,
      "slider_position_X": 1759.3896,
      "slider_value": 8
    },
    {
      "activity": "drawCalled",
      "state": "PinchDetected",
      "cursor_X": 1867.3923,
      "cursor_y": 806.4691,
      "slider_position_X": 1759.3545,
      "slider_value": 8
    },
    {
      "activity": "StateTransition",
      "state": "PinchDetected",
      "message": "Transitioning from states PinchDetected to NoPinchDetected",
      "cursor_X": 1867.3923,
      "cursor_y": 806.4691,
      "slider_position_X": 1759.3545,
      "slider_value": 8
    },
    {
      "activity": "gestureNoLongerDetected",
      "state": "PinchDetected",
      "message": "Gesture no longer detected",
      "cursor_X": 1867.3923,
      "cursor_y": 806.4691,
      "slider_position_X": 1759.3545,
      "slider_value": 8
    },
    {
      "activity": "drawCalled",
      "state": "NoPinchDetected",
      "cursor_X": 1866.1089,
      "cursor_y": 806.8955,
      "slider_position_X": 1759.3545,
      "slider_value": 8
    },
    {
      "activity": "drawCalled",
      "state": "NoPinchDetected",
      "cursor_X": 1863.5735,
      "cursor_y": 807.69257,
      "slider_position_X": 1759.3545,
      "slider_value": 8
    },
    {
      "activity": "drawCalled",
      "state": "NoPinchDetected",
      "cursor_X": 1861.7202,
      "cursor_y": 808.04193,
      "slider_position_X": 1759.3545,
      "slider_value": 8
    },
    {
      "activity": "drawCalled",
      "state": "NoPinchDetected",
      "cursor_X": 1859.7075,
      "cursor_y": 808.2401,
      "slider_position_X": 1759.3545,
      "slider_value": 8
    },
    {
      "activity": "drawCalled",
      "state": "NoPinchDetected",
      "cursor_X": 1858.72,
      "cursor_y": 808.3229,
      "slider_position_X": 1759.3545,
      "slider_value": 8
    },
    {
      "activity": "drawCalled",
      "state": "NoPinchDetected",
      "cursor_X": 1857.3235,
      "cursor_y": 808.4267,
      "slider_position_X": 1759.3545,
      "slider_value": 8
    },
    {
      "activity": "BlockCompleted",
      "state": "NoPinchDetected",
      "message": "Block 7 complete",
      "cursor_X": 1856.9768,
      "cursor_y": 808.4296,
      "slider_position_X": 1759.3545,
      "slider_value": 8
    }
  ]
}